Workbook

Sheet Cover
A1: VAULTA — AUM MODEL v1
A2: Does tokenized-investment AUM overtake the T-bill sleeve in Years 3-5?
A4: THE MODEL
A5: Customers x adoption x monthly contribution (% of wallet balance) x initial rollover at signup, compounding at the expected
A6: investment return, net of redemptions and churn leakage, charged at the AUM fee. Levers are per segment on the Assumptions sheet.
A8: THE ANSWER
B9: Required AUM as a multiple of wallet balances | C9: ='Crossover Analysis'!$C$7 -> 1.92
B10: Year 5 actual AUM / balances | C10: ='Crossover Analysis'!$G$13 -> 0.39943432
B11: Shortfall | C11: ='Crossover Analysis'!$G$15 -> 4.8067978
B12: Does AUM overtake NIM by Year 5? | C12: ='Revenue Comparison'!$G$38 -> no
A14: ANNUAL REVENUE — WHAT VAULTA KEEPS
B15: Metric | C15: Year 1 | D15: Year 2 | E15: Year 3 | F15: Year 4 | G15: Year 5
B16: T-bill NIM (20% sleeve) | C16: ='Revenue Comparison'!$C$32 -> 72866.169 | D16: ='Revenue Comparison'!$D$32 -> 412112.35 | E16: ='Revenue Comparison'!$E$32 -> 1421256.2 | F16: ='Revenue Comparison'!$F$32 -> 3752693 | G16: ='Revenue Comparison'!$G$32 -> 8252607.1
B17: Transaction fees | C17: ='Revenue Comparison'!$C$33 -> 38254.739 | D17: ='Revenue Comparison'!$D$33 -> 216358.99 | E17: ='Revenue Comparison'!$E$33 -> 746159.52 | F17: ='Revenue Comparison'!$F$33 -> 1970163.8 | G17: ='Revenue Comparison'!$G$33 -> 4332618.7
B18: AUM fee | C18: ='Revenue Comparison'!$C$34 -> 0 | D18: ='Revenue Comparison'!$D$34 -> 41461.027 | E18: ='Revenue Comparison'!$E$34 -> 198105.01 | F18: ='Revenue Comparison'!$F$34 -> 682297.66 | G18: ='Revenue Comparison'!$G$34 -> 1695038.8
B19: Total retained revenue | C19: ='Revenue Comparison'!$C$35 -> 111120.91 | D19: ='Revenue Comparison'!$D$35 -> 669932.37 | E19: ='Revenue Comparison'!$E$35 -> 2365520.8 | F19: ='Revenue Comparison'!$F$35 -> 6405154.5 | G19: ='Revenue Comparison'!$G$35 -> 14280265
B20: AUM as % of retained revenue | C20: ='Revenue Comparison'!$C$36 -> 0 | D20: ='Revenue Comparison'!$D$36 -> 0.061888378 | E20: ='Revenue Comparison'!$E$36 -> 0.08374689 | F20: ='Revenue Comparison'!$F$36 -> 0.10652322 | G20: ='Revenue Comparison'!$G$36 -> 0.118698
B21: AUM / NIM ratio | C21: ='Revenue Comparison'!$C$37 -> 0 | D21: ='Revenue Comparison'!$D$37 -> 0.10060613 | E21: ='Revenue Comparison'!$E$37 -> 0.13938726 | F21: ='Revenue Comparison'!$F$37 -> 0.18181547 | G21: ='Revenue Comparison'!$G$37 -> 0.20539435
B22: Closing AUM | C22: ='Revenue Comparison'!$C$39 -> 0 | D22: ='Revenue Comparison'!$D$39 -> 15438488 | E22: ='Revenue Comparison'!$E$39 -> 65492944 | F22: ='Revenue Comparison'!$F$39 -> 2.1191114e+08 | G22: ='Revenue Comparison'!$G$39 -> 4.7482754e+08
B23: Total wallet balances | C23: ='Revenue Comparison'!$C$40 -> 18900000 | D23: ='Revenue Comparison'!$D$40 -> 74681250 | E23: ='Revenue Comparison'!$E$40 -> 237750000 | F23: ='Revenue Comparison'!$F$40 -> 594375000 | G23: ='Revenue Comparison'!$G$40 -> 1188750000
A25: UNIT ECONOMICS AT THE 20/80 SLEEVE
B26: Metric | C26: Year 1 mix | D26: Year 3 mix
B27: Blended CAC | C27: ='Segment Unit Economics'!$H$5 -> 46 | D27: ='Segment Unit Economics'!$I$5 -> 52.75
B28: Blended net contribution / month | C28: ='Segment Unit Economics'!$H$18 -> 2.2355667 | D28: ='Segment Unit Economics'!$I$18 -> 2.7962396
B29: Blended discounted LTV | C29: ='Segment Unit Economics'!$H$22 -> 60.053552 | D29: ='Segment Unit Economics'!$I$22 -> 77.795623
B30: Blended LTV : CAC | C30: ='Segment Unit Economics'!$H$23 -> 1.305512 | D30: ='Segment Unit Economics'!$I$23 -> 1.4747985
B31: AUM share of contribution | C31: ='Segment Unit Economics'!$H$25 -> 0.1922406 | D31: ='Segment Unit Economics'!$I$25 -> 0.14150777
A33: FINDINGS
B34: • AUM does NOT overtake the T-bill sleeve by Year 5 on researched contribution rates. The crossover needs AUM to reach 1.92x total wallet balances; the model reaches a small fraction of that.
B35: • The crossover is a pure ratio and does not depend on how many customers Vaulta has: AUM must exceed (T-bill rate x sleeve) / AUM fee, times wallet balances. Growth alone never triggers it.
B36: • Moving the sleeve to 20/80 makes the crossover EASIER, not harder — it cuts the NIM hurdle from 5.57x balances to 1.92x. But it does so by shrinking the NIM line, not by growing AUM.
B37: • COST OF THE 20/80 SPLIT: blended LTV:CAC falls to 1.47x at the Year 3 mix, against a 3x investability bar. Segment 1 (Underbanked) turns value-destructive at 0.32x and Segment 2 only reaches 1.21x. Only Segments 3 and 4 clear their CAC.
B38: • The monthly drip is not the lever. At 1-3.5% of balance per month, contributions move AUM/balances by roughly adoption x rate x months — far too slowly. The initial rollover at signup is what moves it.
B39: • The 0.50% fee is conservatively priced. Acorns' flat $3/month is about 1.7% of its average balance, so there is real headroom before Vaulta looks expensive.
B40: • Redemption/leakage at 8%/yr is a modelling judgement, not a researched figure. It is the weakest default in the workbook and is flagged on the Research sheet.

Sheet Research & Sources
A1: RESEARCH & SOURCES — basis for every default on the Assumptions sheet
A2: Researched September 2026. Where a source gave a range, the model default sits inside it and the range is stated.
B4: Assumption | C4: Default | D4: Basis | E4: Source
B5: AUM fee | C5: 0.50%/yr | D5: Betterment Basic and Wealthfront both charge 0.25%. Acorns charges a flat $3/mo, which on its ~$2,142 average balance is ~1.7% and ~2.5% on a $1,425 balance. 0.50% sits between the two and undercuts Acorns by ~3x for small accounts. | E5: unbiased.com robo-advisor comparison 2026; acorns.com/learn fee comparison
B6: Avg investment balance (reference point) | C6: $2,142 | D6: Acorns: $30bn AUM across 14m registered users (Jul 2026); $1,876 in 2025, $1,439 in 2024. Closest mass-market analogue to Vaulta's segments. Balance per FUNDED account is higher since registered exceeds funded. | E6: investingintheweb.com/brokers/acorn-statistics
B7: Monthly contribution | C7: ~$50/mo (seg 2) | D7: Acorns reports most customers investing roughly $50-60/month into core accounts. Modelled here as a % of wallet balance so it scales with segment wealth. | E7: investingintheweb.com/brokers/acorn-statistics
B8: Contribution % of balance | C8: 1.0 - 3.5%/mo | D8: US personal saving rate was 2.7-3.0% of income in mid-2026. Top-quintile earners save 15-25%; bottom-quintile saving is negative. Segment rates are scaled to that spread and calibrated so segment 2 lands at the Acorns $50/mo observation. | E8: tradingeconomics.com US personal saving rate; Federal Reserve SCF via Bankrate
B9: Expected investment return | C9: 5.5%/yr | D9: Vanguard's Dec-2025 10-year US equity forecast is 3.9-5.9%; BlackRock's was just over 5% in Sep-2025. Both are well below the historical ~10% and reflect current valuations. 5.5% is the upper-middle of that consensus. | E9: corporate.vanguard.com VEMO 2026; Morningstar 2026 expert forecast survey
B10: Affluent-investor ceiling (reference) | C10: $65-68K | D10: Betterment ~$65bn across 1m+ clients; Wealthfront $95bn across 1.4m+. This is the primary-brokerage tier, roughly 30x the Acorns balance — the gap that decides whether AUM can overtake NIM. | E10: sacra.com robo-advisor research; investingintheweb Betterment statistics
B11: Product is real | C11: Live Aug 2026 | D11: Dinari launched 724 tokenized US stocks including the full S&P 500 for US self-custody wallets, settled in USDC across 4 chains, each dShare backed 1:1 in regulated custody. The Vaulta Invest premise is available today, not speculative. | E11: coindesk.com 2026-08-04; theblock.co/post/410588
B12: Market backdrop | C12: $5.5T by 2030 | D12: Citigroup projects the tokenized securities market reaches $5.5tn by 2030. Ondo has an SEC-aligned framework using iShares Core S&P 500 as collateral, not yet open to US retail. | E12: coindesk.com tokenized equities coverage 2026
B13: Micro-investing growth | C13: +27% YoY | D13: Investment fintech apps grew users 27% year over year, led by micro-investing and fractional-share platforms. Micro-investing platform revenue $0.93bn in 2025 -> $1.85bn by 2029. | E13: globenewswire.com Micro Investing Platforms Market Report 2025-2029
B14: Redemption / leakage | C14: 8%/yr | D14: No clean public disclosure for micro-investing redemption rates. 8% is a modelling judgement, not a researched figure — it is an input and is flagged as the weakest default in the workbook. | E14: MODELLING JUDGEMENT — not sourced

Sheet Assumptions
A1: VAULTA AUM MODEL — ASSUMPTIONS
A2: BLUE = input. BLACK = formula. Defaults are researched; see the Research & Sources sheet for the basis of each.
A4: 1. T-BILL SLEEVE (the revenue AUM is being compared against)
B5: T-bill annual rate | C5: 0.048
B6: Vaulta sleeve % (kept as NIM) | C6: 0.2 | H6: 20/80 split — Vaulta keeps 20%
B7: Consumer reward % (passed through) | C7: =1-C6 -> 0.8
B8: Consumer effective reward rate | C8: =C5*C7 -> 0.0384 | H8: vs Chime 3.75% APY (needs $3k DD)
B9: Vaulta NIM rate on balances | C9: =C5*C6 -> 0.0096
A11: 2. VAULTA INVEST — AUM ENGINE
B12: AUM fee (annual) | C12: 0.005
B13: Expected investment return (annual) | C13: 0.055 | H13: Vanguard 3.9-5.9%, BlackRock ~5%
B14: Annual redemption / leakage rate | C14: 0.08 | H14: modelling judgement — weakest default
C15: Y1 | D15: Y2 | E15: Y3 | F15: Y4 | G15: Y5
B16: Product availability ramp | C16: 0 | D16: 0.45 | E16: 0.7 | F16: 0.9 | G16: 1 | H16: scales each segment's ceiling
A17: One adoption mechanism only: effective adoption = segment ceiling x availability ramp. Avoids the two-schedule conflict in the Pay-Model.
A19: 3. SEGMENT LEVERS
B20: Segment | C20: CAC | D20: Wallet balance | E20: Monthly churn | F20: AUM adoption ceiling | G20: Monthly contribution (% of balance) | H20: Initial rollover at signup (x wallet balance)
B21: 1 — Underbanked Active | C21: 40 | D21: 900 | E21: 0.0325 | F21: 0.08 | G21: 0.01 | H21: 0.25
B22: 2 — Dissatisfied Banked | C22: 57.5 | D22: 2500 | E22: 0.0225 | F22: 0.25 | G22: 0.02 | H22: 0.6
B23: 3 — Primary Bank Switcher | C23: 70 | D23: 4250 | E23: 0.0125 | F23: 0.4 | G23: 0.025 | H23: 1
B24: 4 — Crypto-Curious Investor | C24: 47.5 | D24: 6000 | E24: 0.015 | F24: 0.7 | G24: 0.035 | H24: 2
B26: memo: implied monthly contribution ($)
B27: 1 — Underbanked Active | C27: =D21*G21 -> 9
B28: 2 — Dissatisfied Banked | C28: =D22*G22 -> 50
B29: 3 — Primary Bank Switcher | C29: =D23*G23 -> 106.25
B30: 4 — Crypto-Curious Investor | C30: =D24*G24 -> 210
A31: Segment 2 lands near the ~$50/month Acorns observation. Initial rollover is the lump sum a new investor transfers in at signup, as a multiple of wallet balance.
A33: 4. SEGMENT MIX BY YEAR
B34: Segment | C34: Y1 | D34: Y2 | E34: Y3 | F34: Y4 | G34: Y5
B35: 1 — Underbanked Active | C35: 0.6 | D35: 0.475 | E35: 0.35 | F35: 0.35 | G35: 0.35
B36: 2 — Dissatisfied Banked | C36: 0.3 | D36: 0.375 | E36: 0.45 | F36: 0.45 | G36: 0.45
B37: 3 — Primary Bank Switcher | C37: 0 | D37: 0.075 | E37: 0.15 | F37: 0.15 | G37: 0.15
B38: 4 — Crypto-Curious Investor | C38: 0.1 | D38: 0.075 | E38: 0.05 | F38: 0.05 | G38: 0.05
B39: Total | C39: =SUM(C35:C38) -> 1 | D39: =SUM(D35:D38) -> 1 | E39: =SUM(E35:E38) -> 1 | F39: =SUM(F35:F38) -> 1 | G39: =SUM(G35:G38) -> 1
A41: 5. CONSUMER GROWTH
B42: Starting active consumers (Q0) | C42: 1000
C43: Y1 | D43: Y2 | E43: Y3 | F43: Y4 | G43: Y5
B44: Year-end active consumers | C44: 10000 | D44: 35000 | E44: 100000 | F44: 250000 | G44: 500000
A46: 6. TRANSACTION FEES & COSTS (context for unit economics)
B47: Monthly spend as % of balance | C47: 0.2
B48: Share of spend on QR / Solana Pay | C48: 0.4
B49: Share of spend on Rain card | C49: =1-C48 -> 0.6
B50: QR merchant fee | C50: 0.005
B51: Rain net interchange | C51: 0.0035
B52: Rain per-transaction cost | C52: 0.15
B53: Average transaction size | C53: 45
B54: Infra per consumer / month | C54: 0.5
A56: 7. LTV DISCOUNTING
B57: WACC | C57: 0.15
B58: Monthly discount rate | C58: =(1+C57)^(1/12)-1 -> 0.011714917
B59: LTV horizon (months) | C59: 60

Sheet Consumer Model
A1: CONSUMER MODEL — quarterly ramp by segment
B5: Quarter | C5: 1 | D5: 2 | E5: 3 | F5: 4 | G5: 5 | H5: 6 | I5: 7 | J5: 8 | K5: 9 | L5: 10 | M5: 11 | N5: 12 | O5: 13 | P5: 14 | Q5: 15 | R5: 16 | S5: 17 | T5: 18 | U5: 19 | V5: 20
B6: Year | C6: =INT((C5-1)/4)+1 -> 1 | D6: =INT((D5-1)/4)+1 -> 1 | E6: =INT((E5-1)/4)+1 -> 1 | F6: =INT((F5-1)/4)+1 -> 1 | G6: =INT((G5-1)/4)+1 -> 2 | H6: =INT((H5-1)/4)+1 -> 2 | I6: =INT((I5-1)/4)+1 -> 2 | J6: =INT((J5-1)/4)+1 -> 2 | ... V6: =INT((V5-1)/4)+1 -> 5
B7: Period | C7: 2027 Q1 | D7: 2027 Q2 | E7: 2027 Q3 | F7: 2027 Q4 | G7: 2028 Q1 | H7: 2028 Q2 | I7: 2028 Q3 | J7: 2028 Q4 | K7: 2029 Q1 | L7: 2029 Q2 | M7: 2029 Q3 | N7: 2029 Q4 | O7: 2030 Q1 | P7: 2030 Q2 | Q7: 2030 Q3 | R7: 2030 Q4 | S7: 2031 Q1 | T7: 2031 Q2 | U7: 2031 Q3 | V7: 2031 Q4
A9: ACTIVE CONSUMERS
B10: Year-end target | C10: =INDEX(Assumptions!$C$44:$G$44,1,'Consumer Model'!C$6) -> 10000 | D10: =INDEX(Assumptions!$C$44:$G$44,1,'Consumer Model'!D$6) -> 10000 | E10: =INDEX(Assumptions!$C$44:$G$44,1,'Consumer Model'!E$6) -> 10000 | F10: =INDEX(Assumptions!$C$44:$G$44,1,'Consumer Model'!F$6) -> 10000 | G10: =INDEX(Assumptions!$C$44:$G$44,1,'Consumer Model'!G$6) -> 35000 | H10: =INDEX(Assumptions!$C$44:$G$44,1,'Consumer Model'!H$6) -> 35000 | I10: =INDEX(Assumptions!$C$44:$G$44,1,'Consumer Model'!I$6) -> 35000 | J10: =INDEX(Assumptions!$C$44:$G$44,1,'Consumer Model'!J$6) -> 35000 | ... V10: =INDEX(Assumptions!$C$44:$G$44,1,'Consumer Model'!V$6) -> 500000
B11: Prior year-end base | C11: =IF('Consumer Model'!C$6=1,Assumptions!$C$42,INDEX(Assumptions!$C$44:$G$44,1,'Consumer Model'!C$6-1)) -> 1000 | D11: =IF('Consumer Model'!D$6=1,Assumptions!$C$42,INDEX(Assumptions!$C$44:$G$44,1,'Consumer Model'!D$6-1)) -> 1000 | E11: =IF('Consumer Model'!E$6=1,Assumptions!$C$42,INDEX(Assumptions!$C$44:$G$44,1,'Consumer Model'!E$6-1)) -> 1000 | F11: =IF('Consumer Model'!F$6=1,Assumptions!$C$42,INDEX(Assumptions!$C$44:$G$44,1,'Consumer Model'!F$6-1)) -> 1000 | G11: =IF('Consumer Model'!G$6=1,Assumptions!$C$42,INDEX(Assumptions!$C$44:$G$44,1,'Consumer Model'!G$6-1)) -> 10000 | H11: =IF('Consumer Model'!H$6=1,Assumptions!$C$42,INDEX(Assumptions!$C$44:$G$44,1,'Consumer Model'!H$6-1)) -> 10000 | I11: =IF('Consumer Model'!I$6=1,Assumptions!$C$42,INDEX(Assumptions!$C$44:$G$44,1,'Consumer Model'!I$6-1)) -> 10000 | J11: =IF('Consumer Model'!J$6=1,Assumptions!$C$42,INDEX(Assumptions!$C$44:$G$44,1,'Consumer Model'!J$6-1)) -> 10000 | ... V11: =IF('Consumer Model'!V$6=1,Assumptions!$C$42,INDEX(Assumptions!$C$44:$G$44,1,'Consumer Model'!V$6-1)) -> 250000
B12: Active consumers (end of period) | C12: =C11*(C10/C11)^((C5-('Consumer Model'!C$6-1)*4)/4) -> 1778.2794 | D12: =D11*(D10/D11)^((D5-('Consumer Model'!D$6-1)*4)/4) -> 3162.2777 | E12: =E11*(E10/E11)^((E5-('Consumer Model'!E$6-1)*4)/4) -> 5623.4133 | F12: =F11*(F10/F11)^((F5-('Consumer Model'!F$6-1)*4)/4) -> 10000 | G12: =G11*(G10/G11)^((G5-('Consumer Model'!G$6-1)*4)/4) -> 13677.824 | H12: =H11*(H10/H11)^((H5-('Consumer Model'!H$6-1)*4)/4) -> 18708.287 | I12: =I11*(I10/I11)^((I5-('Consumer Model'!I$6-1)*4)/4) -> 25588.866 | J12: =J11*(J10/J11)^((J5-('Consumer Model'!J$6-1)*4)/4) -> 35000 | ... V12: =V11*(V10/V11)^((V5-('Consumer Model'!V$6-1)*4)/4) -> 500000
B13: Active consumers (beginning) | C13: =Assumptions!$C$42 -> 1000 | D13: =C12 -> 1778.2794 | E13: =D12 -> 3162.2777 | F13: =E12 -> 5623.4133 | G13: =F12 -> 10000 | H13: =G12 -> 13677.824 | I13: =H12 -> 18708.287 | J13: =I12 -> 25588.866 | K13: =J12 -> 35000 | ... V13: =U12 -> 420448.21
B14: Active consumers (average) | C14: =(C13+C12)/2 -> 1389.1397 | D14: =(D13+D12)/2 -> 2470.2785 | E14: =(E13+E12)/2 -> 4392.8455 | F14: =(F13+F12)/2 -> 7811.7066 | G14: =(G13+G12)/2 -> 11838.912 | H14: =(H13+H12)/2 -> 16193.055 | I14: =(I13+I12)/2 -> 22148.576 | J14: =(J13+J12)/2 -> 30294.433 | ... V14: =(V13+V12)/2 -> 460224.1
B15: Blended monthly churn | C15: =SUMPRODUCT(Assumptions!$E$21:$E$24,INDEX(Assumptions!$C$35:$G$38,0,'Consumer Model'!C$6)) -> 0.02775 | D15: =SUMPRODUCT(Assumptions!$E$21:$E$24,INDEX(Assumptions!$C$35:$G$38,0,'Consumer Model'!D$6)) -> 0.02775 | E15: =SUMPRODUCT(Assumptions!$E$21:$E$24,INDEX(Assumptions!$C$35:$G$38,0,'Consumer Model'!E$6)) -> 0.02775 | F15: =SUMPRODUCT(Assumptions!$E$21:$E$24,INDEX(Assumptions!$C$35:$G$38,0,'Consumer Model'!F$6)) -> 0.02775 | G15: =SUMPRODUCT(Assumptions!$E$21:$E$24,INDEX(Assumptions!$C$35:$G$38,0,'Consumer Model'!G$6)) -> 0.0259375 | H15: =SUMPRODUCT(Assumptions!$E$21:$E$24,INDEX(Assumptions!$C$35:$G$38,0,'Consumer Model'!H$6)) -> 0.0259375 | I15: =SUMPRODUCT(Assumptions!$E$21:$E$24,INDEX(Assumptions!$C$35:$G$38,0,'Consumer Model'!I$6)) -> 0.0259375 | J15: =SUMPRODUCT(Assumptions!$E$21:$E$24,INDEX(Assumptions!$C$35:$G$38,0,'Consumer Model'!J$6)) -> 0.0259375 | ... V15: =SUMPRODUCT(Assumptions!$E$21:$E$24,INDEX(Assumptions!$C$35:$G$38,0,'Consumer Model'!V$6)) -> 0.024125
B16: Quarterly churn rate | C16: =1-(1-C15)^3 -> 0.080961182 | D16: =1-(1-D15)^3 -> 0.080961182 | E16: =1-(1-E15)^3 -> 0.080961182 | F16: =1-(1-F15)^3 -> 0.080961182 | G16: =1-(1-G15)^3 -> 0.075811688 | H16: =1-(1-H15)^3 -> 0.075811688 | I16: =1-(1-I15)^3 -> 0.075811688 | J16: =1-(1-J15)^3 -> 0.075811688 | ... V16: =1-(1-V15)^3 -> 0.070642994
B17: Blended CAC | C17: =SUMPRODUCT(Assumptions!$C$21:$C$24,INDEX(Assumptions!$C$35:$G$38,0,'Consumer Model'!C$6)) -> 46 | D17: =SUMPRODUCT(Assumptions!$C$21:$C$24,INDEX(Assumptions!$C$35:$G$38,0,'Consumer Model'!D$6)) -> 46 | E17: =SUMPRODUCT(Assumptions!$C$21:$C$24,INDEX(Assumptions!$C$35:$G$38,0,'Consumer Model'!E$6)) -> 46 | F17: =SUMPRODUCT(Assumptions!$C$21:$C$24,INDEX(Assumptions!$C$35:$G$38,0,'Consumer Model'!F$6)) -> 46 | G17: =SUMPRODUCT(Assumptions!$C$21:$C$24,INDEX(Assumptions!$C$35:$G$38,0,'Consumer Model'!G$6)) -> 49.375 | H17: =SUMPRODUCT(Assumptions!$C$21:$C$24,INDEX(Assumptions!$C$35:$G$38,0,'Consumer Model'!H$6)) -> 49.375 | I17: =SUMPRODUCT(Assumptions!$C$21:$C$24,INDEX(Assumptions!$C$35:$G$38,0,'Consumer Model'!I$6)) -> 49.375 | J17: =SUMPRODUCT(Assumptions!$C$21:$C$24,INDEX(Assumptions!$C$35:$G$38,0,'Consumer Model'!J$6)) -> 49.375 | ... V17: =SUMPRODUCT(Assumptions!$C$21:$C$24,INDEX(Assumptions!$C$35:$G$38,0,'Consumer Model'!V$6)) -> 52.75
B18: Blended wallet balance | C18: =SUMPRODUCT(Assumptions!$D$21:$D$24,INDEX(Assumptions!$C$35:$G$38,0,'Consumer Model'!C$6)) -> 1890 | D18: =SUMPRODUCT(Assumptions!$D$21:$D$24,INDEX(Assumptions!$C$35:$G$38,0,'Consumer Model'!D$6)) -> 1890 | E18: =SUMPRODUCT(Assumptions!$D$21:$D$24,INDEX(Assumptions!$C$35:$G$38,0,'Consumer Model'!E$6)) -> 1890 | F18: =SUMPRODUCT(Assumptions!$D$21:$D$24,INDEX(Assumptions!$C$35:$G$38,0,'Consumer Model'!F$6)) -> 1890 | G18: =SUMPRODUCT(Assumptions!$D$21:$D$24,INDEX(Assumptions!$C$35:$G$38,0,'Consumer Model'!G$6)) -> 2133.75 | H18: =SUMPRODUCT(Assumptions!$D$21:$D$24,INDEX(Assumptions!$C$35:$G$38,0,'Consumer Model'!H$6)) -> 2133.75 | I18: =SUMPRODUCT(Assumptions!$D$21:$D$24,INDEX(Assumptions!$C$35:$G$38,0,'Consumer Model'!I$6)) -> 2133.75 | J18: =SUMPRODUCT(Assumptions!$D$21:$D$24,INDEX(Assumptions!$C$35:$G$38,0,'Consumer Model'!J$6)) -> 2133.75 | ... V18: =SUMPRODUCT(Assumptions!$D$21:$D$24,INDEX(Assumptions!$C$35:$G$38,0,'Consumer Model'!V$6)) -> 2377.5
B19: TOTAL WALLET BALANCES (avg) | C19: =C14*C18 -> 2625474 | D19: =D14*D18 -> 4668826.4 | E19: =E14*E18 -> 8302477.9 | F19: =F14*F18 -> 14764126 | G19: =G14*G18 -> 25261278 | H19: =H14*H18 -> 34551932 | I19: =I14*I18 -> 47259525 | J19: =J14*J18 -> 64640746 | ... V19: =V14*V18 -> 1.0941828e+09
B20: TOTAL WALLET BALANCES (end of period) | C20: =C12*C18 -> 3360948.1 | D20: =D12*D18 -> 5976704.8 | E20: =E12*E18 -> 10628251 | F20: =F12*F18 -> 18900000 | G20: =G12*G18 -> 29185057 | H20: =H12*H18 -> 39918807 | I20: =I12*I18 -> 54600242 | J20: =J12*J18 -> 74681250 | ... V20: =V12*V18 -> 1188750000
A21: Revenue uses the AVERAGE balance (income accrues over the quarter). The crossover ratio uses the END-OF-PERIOD balance, because it compares two stocks.
A23: ACTIVE CONSUMERS BY SEGMENT (end of period)
B24: 1 — Underbanked Active | C24: =C12*INDEX(Assumptions!$C$35:$G$38,1,'Consumer Model'!C$6) -> 1066.9676 | D24: =D12*INDEX(Assumptions!$C$35:$G$38,1,'Consumer Model'!D$6) -> 1897.3666 | E24: =E12*INDEX(Assumptions!$C$35:$G$38,1,'Consumer Model'!E$6) -> 3374.048 | F24: =F12*INDEX(Assumptions!$C$35:$G$38,1,'Consumer Model'!F$6) -> 6000 | G24: =G12*INDEX(Assumptions!$C$35:$G$38,1,'Consumer Model'!G$6) -> 6496.9664 | H24: =H12*INDEX(Assumptions!$C$35:$G$38,1,'Consumer Model'!H$6) -> 8886.4363 | I24: =I12*INDEX(Assumptions!$C$35:$G$38,1,'Consumer Model'!I$6) -> 12154.711 | J24: =J12*INDEX(Assumptions!$C$35:$G$38,1,'Consumer Model'!J$6) -> 16625 | ... V24: =V12*INDEX(Assumptions!$C$35:$G$38,1,'Consumer Model'!V$6) -> 175000
B25: 2 — Dissatisfied Banked | C25: =C12*INDEX(Assumptions!$C$35:$G$38,2,'Consumer Model'!C$6) -> 533.48382 | D25: =D12*INDEX(Assumptions!$C$35:$G$38,2,'Consumer Model'!D$6) -> 948.6833 | E25: =E12*INDEX(Assumptions!$C$35:$G$38,2,'Consumer Model'!E$6) -> 1687.024 | F25: =F12*INDEX(Assumptions!$C$35:$G$38,2,'Consumer Model'!F$6) -> 3000 | G25: =G12*INDEX(Assumptions!$C$35:$G$38,2,'Consumer Model'!G$6) -> 5129.184 | H25: =H12*INDEX(Assumptions!$C$35:$G$38,2,'Consumer Model'!H$6) -> 7015.6076 | I25: =I12*INDEX(Assumptions!$C$35:$G$38,2,'Consumer Model'!I$6) -> 9595.8246 | J25: =J12*INDEX(Assumptions!$C$35:$G$38,2,'Consumer Model'!J$6) -> 13125 | ... V25: =V12*INDEX(Assumptions!$C$35:$G$38,2,'Consumer Model'!V$6) -> 225000
B26: 3 — Primary Bank Switcher | C26: =C12*INDEX(Assumptions!$C$35:$G$38,3,'Consumer Model'!C$6) -> 0 | D26: =D12*INDEX(Assumptions!$C$35:$G$38,3,'Consumer Model'!D$6) -> 0 | E26: =E12*INDEX(Assumptions!$C$35:$G$38,3,'Consumer Model'!E$6) -> 0 | F26: =F12*INDEX(Assumptions!$C$35:$G$38,3,'Consumer Model'!F$6) -> 0 | G26: =G12*INDEX(Assumptions!$C$35:$G$38,3,'Consumer Model'!G$6) -> 1025.8368 | H26: =H12*INDEX(Assumptions!$C$35:$G$38,3,'Consumer Model'!H$6) -> 1403.1215 | I26: =I12*INDEX(Assumptions!$C$35:$G$38,3,'Consumer Model'!I$6) -> 1919.1649 | J26: =J12*INDEX(Assumptions!$C$35:$G$38,3,'Consumer Model'!J$6) -> 2625 | ... V26: =V12*INDEX(Assumptions!$C$35:$G$38,3,'Consumer Model'!V$6) -> 75000
B27: 4 — Crypto-Curious Investor | C27: =C12*INDEX(Assumptions!$C$35:$G$38,4,'Consumer Model'!C$6) -> 177.82794 | D27: =D12*INDEX(Assumptions!$C$35:$G$38,4,'Consumer Model'!D$6) -> 316.22777 | E27: =E12*INDEX(Assumptions!$C$35:$G$38,4,'Consumer Model'!E$6) -> 562.34133 | F27: =F12*INDEX(Assumptions!$C$35:$G$38,4,'Consumer Model'!F$6) -> 1000 | G27: =G12*INDEX(Assumptions!$C$35:$G$38,4,'Consumer Model'!G$6) -> 1025.8368 | H27: =H12*INDEX(Assumptions!$C$35:$G$38,4,'Consumer Model'!H$6) -> 1403.1215 | I27: =I12*INDEX(Assumptions!$C$35:$G$38,4,'Consumer Model'!I$6) -> 1919.1649 | J27: =J12*INDEX(Assumptions!$C$35:$G$38,4,'Consumer Model'!J$6) -> 2625 | ... V27: =V12*INDEX(Assumptions!$C$35:$G$38,4,'Consumer Model'!V$6) -> 25000
A29: ACTIVE CONSUMERS BY SEGMENT (average)
B30: 1 — Underbanked Active | C30: =C14*INDEX(Assumptions!$C$35:$G$38,1,'Consumer Model'!C$6) -> 833.48382 | D30: =D14*INDEX(Assumptions!$C$35:$G$38,1,'Consumer Model'!D$6) -> 1482.1671 | E30: =E14*INDEX(Assumptions!$C$35:$G$38,1,'Consumer Model'!E$6) -> 2635.7073 | F30: =F14*INDEX(Assumptions!$C$35:$G$38,1,'Consumer Model'!F$6) -> 4687.024 | G30: =G14*INDEX(Assumptions!$C$35:$G$38,1,'Consumer Model'!G$6) -> 5623.4832 | H30: =H14*INDEX(Assumptions!$C$35:$G$38,1,'Consumer Model'!H$6) -> 7691.7013 | I30: =I14*INDEX(Assumptions!$C$35:$G$38,1,'Consumer Model'!I$6) -> 10520.574 | J30: =J14*INDEX(Assumptions!$C$35:$G$38,1,'Consumer Model'!J$6) -> 14389.856 | ... V30: =V14*INDEX(Assumptions!$C$35:$G$38,1,'Consumer Model'!V$6) -> 161078.44
B31: 2 — Dissatisfied Banked | C31: =C14*INDEX(Assumptions!$C$35:$G$38,2,'Consumer Model'!C$6) -> 416.74191 | D31: =D14*INDEX(Assumptions!$C$35:$G$38,2,'Consumer Model'!D$6) -> 741.08356 | E31: =E14*INDEX(Assumptions!$C$35:$G$38,2,'Consumer Model'!E$6) -> 1317.8536 | F31: =F14*INDEX(Assumptions!$C$35:$G$38,2,'Consumer Model'!F$6) -> 2343.512 | G31: =G14*INDEX(Assumptions!$C$35:$G$38,2,'Consumer Model'!G$6) -> 4439.592 | H31: =H14*INDEX(Assumptions!$C$35:$G$38,2,'Consumer Model'!H$6) -> 6072.3958 | I31: =I14*INDEX(Assumptions!$C$35:$G$38,2,'Consumer Model'!I$6) -> 8305.7161 | J31: =J14*INDEX(Assumptions!$C$35:$G$38,2,'Consumer Model'!J$6) -> 11360.412 | ... V31: =V14*INDEX(Assumptions!$C$35:$G$38,2,'Consumer Model'!V$6) -> 207100.85
B32: 3 — Primary Bank Switcher | C32: =C14*INDEX(Assumptions!$C$35:$G$38,3,'Consumer Model'!C$6) -> 0 | D32: =D14*INDEX(Assumptions!$C$35:$G$38,3,'Consumer Model'!D$6) -> 0 | E32: =E14*INDEX(Assumptions!$C$35:$G$38,3,'Consumer Model'!E$6) -> 0 | F32: =F14*INDEX(Assumptions!$C$35:$G$38,3,'Consumer Model'!F$6) -> 0 | G32: =G14*INDEX(Assumptions!$C$35:$G$38,3,'Consumer Model'!G$6) -> 887.9184 | H32: =H14*INDEX(Assumptions!$C$35:$G$38,3,'Consumer Model'!H$6) -> 1214.4792 | I32: =I14*INDEX(Assumptions!$C$35:$G$38,3,'Consumer Model'!I$6) -> 1661.1432 | J32: =J14*INDEX(Assumptions!$C$35:$G$38,3,'Consumer Model'!J$6) -> 2272.0825 | ... V32: =V14*INDEX(Assumptions!$C$35:$G$38,3,'Consumer Model'!V$6) -> 69033.616
B33: 4 — Crypto-Curious Investor | C33: =C14*INDEX(Assumptions!$C$35:$G$38,4,'Consumer Model'!C$6) -> 138.91397 | D33: =D14*INDEX(Assumptions!$C$35:$G$38,4,'Consumer Model'!D$6) -> 247.02785 | E33: =E14*INDEX(Assumptions!$C$35:$G$38,4,'Consumer Model'!E$6) -> 439.28455 | F33: =F14*INDEX(Assumptions!$C$35:$G$38,4,'Consumer Model'!F$6) -> 781.17066 | G33: =G14*INDEX(Assumptions!$C$35:$G$38,4,'Consumer Model'!G$6) -> 887.9184 | H33: =H14*INDEX(Assumptions!$C$35:$G$38,4,'Consumer Model'!H$6) -> 1214.4792 | I33: =I14*INDEX(Assumptions!$C$35:$G$38,4,'Consumer Model'!I$6) -> 1661.1432 | J33: =J14*INDEX(Assumptions!$C$35:$G$38,4,'Consumer Model'!J$6) -> 2272.0825 | ... V33: =V14*INDEX(Assumptions!$C$35:$G$38,4,'Consumer Model'!V$6) -> 23011.205

Sheet AUM Engine
A1: AUM ENGINE — quarterly roll-forward by segment
A2: Closing AUM = opening + initial rollovers + contributions - redemptions - churn leakage + market return. Fee is charged on average AUM.
B5: Quarter | C5: 1 | D5: 2 | E5: 3 | F5: 4 | G5: 5 | H5: 6 | I5: 7 | J5: 8 | K5: 9 | L5: 10 | M5: 11 | N5: 12 | O5: 13 | P5: 14 | Q5: 15 | R5: 16 | S5: 17 | T5: 18 | U5: 19 | V5: 20
B6: Year | C6: =INT((C5-1)/4)+1 -> 1 | D6: =INT((D5-1)/4)+1 -> 1 | E6: =INT((E5-1)/4)+1 -> 1 | F6: =INT((F5-1)/4)+1 -> 1 | G6: =INT((G5-1)/4)+1 -> 2 | H6: =INT((H5-1)/4)+1 -> 2 | I6: =INT((I5-1)/4)+1 -> 2 | J6: =INT((J5-1)/4)+1 -> 2 | ... V6: =INT((V5-1)/4)+1 -> 5
B7: Period | C7: 2027 Q1 | D7: 2027 Q2 | E7: 2027 Q3 | F7: 2027 Q4 | G7: 2028 Q1 | H7: 2028 Q2 | I7: 2028 Q3 | J7: 2028 Q4 | K7: 2029 Q1 | L7: 2029 Q2 | M7: 2029 Q3 | N7: 2029 Q4 | O7: 2030 Q1 | P7: 2030 Q2 | Q7: 2030 Q3 | R7: 2030 Q4 | S7: 2031 Q1 | T7: 2031 Q2 | U7: 2031 Q3 | V7: 2031 Q4
A9: SEGMENT 1 — Underbanked Active
B10: Invest users (end of period) | C10: ='Consumer Model'!C24*Assumptions!$F$21*INDEX(Assumptions!$C$16:$G$16,1,'Consumer Model'!C$6) -> 0 | D10: ='Consumer Model'!D24*Assumptions!$F$21*INDEX(Assumptions!$C$16:$G$16,1,'Consumer Model'!D$6) -> 0 | E10: ='Consumer Model'!E24*Assumptions!$F$21*INDEX(Assumptions!$C$16:$G$16,1,'Consumer Model'!E$6) -> 0 | F10: ='Consumer Model'!F24*Assumptions!$F$21*INDEX(Assumptions!$C$16:$G$16,1,'Consumer Model'!F$6) -> 0 | G10: ='Consumer Model'!G24*Assumptions!$F$21*INDEX(Assumptions!$C$16:$G$16,1,'Consumer Model'!G$6) -> 233.89079 | H10: ='Consumer Model'!H24*Assumptions!$F$21*INDEX(Assumptions!$C$16:$G$16,1,'Consumer Model'!H$6) -> 319.91171 | I10: ='Consumer Model'!I24*Assumptions!$F$21*INDEX(Assumptions!$C$16:$G$16,1,'Consumer Model'!I$6) -> 437.5696 | J10: ='Consumer Model'!J24*Assumptions!$F$21*INDEX(Assumptions!$C$16:$G$16,1,'Consumer Model'!J$6) -> 598.5 | ... V10: ='Consumer Model'!V24*Assumptions!$F$21*INDEX(Assumptions!$C$16:$G$16,1,'Consumer Model'!V$6) -> 14000
B11: New invest users | C11: =C10 -> 0 | D11: =MAX(0,D10-C10) -> 0 | E11: =MAX(0,E10-D10) -> 0 | F11: =MAX(0,F10-E10) -> 0 | G11: =MAX(0,G10-F10) -> 233.89079 | H11: =MAX(0,H10-G10) -> 86.020916 | I11: =MAX(0,I10-H10) -> 117.6579 | J11: =MAX(0,J10-I10) -> 160.9304 | K11: =MAX(0,K10-J10) -> 293.3814 | ... V11: =MAX(0,V10-U10) -> 2227.4502
B12: Opening AUM | C12: =0 -> 0 | D12: =C18 -> 0 | E12: =D18 -> 0 | F12: =E18 -> 0 | G12: =F18 -> 0 | H12: =G18 -> 59337.596 | I12: =H18 -> 81531.925 | J12: =I18 -> 111851.51 | K12: =J18 -> 153288.44 | ... V12: =U18 -> 3040069.8
B13: + Initial rollovers | C13: =C11*Assumptions!$D$21*Assumptions!$H$21 -> 0 | D13: =D11*Assumptions!$D$21*Assumptions!$H$21 -> 0 | E13: =E11*Assumptions!$D$21*Assumptions!$H$21 -> 0 | F13: =F11*Assumptions!$D$21*Assumptions!$H$21 -> 0 | G13: =G11*Assumptions!$D$21*Assumptions!$H$21 -> 52625.428 | H13: =H11*Assumptions!$D$21*Assumptions!$H$21 -> 19354.706 | I13: =I11*Assumptions!$D$21*Assumptions!$H$21 -> 26473.026 | J13: =J11*Assumptions!$D$21*Assumptions!$H$21 -> 36209.34 | ... V13: =V11*Assumptions!$D$21*Assumptions!$H$21 -> 501176.29
B14: + Contributions | C14: =C10*Assumptions!$D$21*Assumptions!$G$21*3 -> 0 | D14: =D10*Assumptions!$D$21*Assumptions!$G$21*3 -> 0 | E14: =E10*Assumptions!$D$21*Assumptions!$G$21*3 -> 0 | F14: =F10*Assumptions!$D$21*Assumptions!$G$21*3 -> 0 | G14: =G10*Assumptions!$D$21*Assumptions!$G$21*3 -> 6315.0513 | H14: =H10*Assumptions!$D$21*Assumptions!$G$21*3 -> 8637.6161 | I14: =I10*Assumptions!$D$21*Assumptions!$G$21*3 -> 11814.379 | J14: =J10*Assumptions!$D$21*Assumptions!$G$21*3 -> 16159.5 | ... V14: =V10*Assumptions!$D$21*Assumptions!$G$21*3 -> 378000
B15: - Redemptions | C15: =-C12*Assumptions!$C$14/4 -> 0 | D15: =-D12*Assumptions!$C$14/4 -> 0 | E15: =-E12*Assumptions!$C$14/4 -> 0 | F15: =-F12*Assumptions!$C$14/4 -> 0 | G15: =-G12*Assumptions!$C$14/4 -> 0 | H15: =-H12*Assumptions!$C$14/4 -> -1186.7519 | I15: =-I12*Assumptions!$C$14/4 -> -1630.6385 | J15: =-J12*Assumptions!$C$14/4 -> -2237.0301 | ... V15: =-V12*Assumptions!$C$14/4 -> -60801.397
B16: - Churn leakage | C16: =-C12*(1-(1-Assumptions!$E$21)^3) -> 0 | D16: =-D12*(1-(1-Assumptions!$E$21)^3) -> 0 | E16: =-E12*(1-(1-Assumptions!$E$21)^3) -> 0 | F16: =-F12*(1-(1-Assumptions!$E$21)^3) -> 0 | G16: =-G12*(1-(1-Assumptions!$E$21)^3) -> 0 | H16: =-H12*(1-(1-Assumptions!$E$21)^3) -> -5599.4265 | I16: =-I12*(1-(1-Assumptions!$E$21)^3) -> -7693.8072 | J16: =-J12*(1-(1-Assumptions!$E$21)^3) -> -10554.932 | ... V16: =-V12*(1-(1-Assumptions!$E$21)^3) -> -286877.95
B17: + Market return | C17: =(C12+(C13+C14)/2)*((1+Assumptions!$C$13)^(1/4)-1) -> 0 | D17: =(D12+(D13+D14)/2)*((1+Assumptions!$C$13)^(1/4)-1) -> 0 | E17: =(E12+(E13+E14)/2)*((1+Assumptions!$C$13)^(1/4)-1) -> 0 | F17: =(F12+(F13+F14)/2)*((1+Assumptions!$C$13)^(1/4)-1) -> 0 | G17: =(G12+(G13+G14)/2)*((1+Assumptions!$C$13)^(1/4)-1) -> 397.11662 | H17: =(H12+(H13+H14)/2)*((1+Assumptions!$C$13)^(1/4)-1) -> 988.18517 | I17: =(I12+(I13+I14)/2)*((1+Assumptions!$C$13)^(1/4)-1) -> 1356.6216 | J17: =(J12+(J13+J14)/2)*((1+Assumptions!$C$13)^(1/4)-1) -> 1860.0582 | ... V17: =(V12+(V13+V14)/2)*((1+Assumptions!$C$13)^(1/4)-1) -> 46888.998
B18: CLOSING AUM | C18: =C12+C13+C14+C15+C16+C17 -> 0 | D18: =D12+D13+D14+D15+D16+D17 -> 0 | E18: =E12+E13+E14+E15+E16+E17 -> 0 | F18: =F12+F13+F14+F15+F16+F17 -> 0 | G18: =G12+G13+G14+G15+G16+G17 -> 59337.596 | H18: =H12+H13+H14+H15+H16+H17 -> 81531.925 | I18: =I12+I13+I14+I15+I16+I17 -> 111851.51 | J18: =J12+J13+J14+J15+J16+J17 -> 153288.44 | ... V18: =V12+V13+V14+V15+V16+V17 -> 3618455.8
B19: Average AUM | C19: =(C12+C18)/2 -> 0 | D19: =(D12+D18)/2 -> 0 | E19: =(E12+E18)/2 -> 0 | F19: =(F12+F18)/2 -> 0 | G19: =(G12+G18)/2 -> 29668.798 | H19: =(H12+H18)/2 -> 70434.76 | I19: =(I12+I18)/2 -> 96691.716 | J19: =(J12+J18)/2 -> 132569.97 | ... V19: =(V12+V18)/2 -> 3329262.8
B20: AUM per invest user | C20: =IF(C10=0,0,C18/C10) -> 0 | D20: =IF(D10=0,0,D18/D10) -> 0 | E20: =IF(E10=0,0,E18/E10) -> 0 | F20: =IF(F10=0,0,F18/F10) -> 0 | G20: =IF(G10=0,0,G18/G10) -> 253.69787 | H20: =IF(H10=0,0,H18/H10) -> 254.85758 | I20: =IF(I10=0,0,I18/I10) -> 255.61992 | J20: =IF(J10=0,0,J18/J10) -> 256.12104 | ... V20: =IF(V10=0,0,V18/V10) -> 258.46113
A22: SEGMENT 2 — Dissatisfied Banked
B23: Invest users (end of period) | C23: ='Consumer Model'!C25*Assumptions!$F$22*INDEX(Assumptions!$C$16:$G$16,1,'Consumer Model'!C$6) -> 0 | D23: ='Consumer Model'!D25*Assumptions!$F$22*INDEX(Assumptions!$C$16:$G$16,1,'Consumer Model'!D$6) -> 0 | E23: ='Consumer Model'!E25*Assumptions!$F$22*INDEX(Assumptions!$C$16:$G$16,1,'Consumer Model'!E$6) -> 0 | F23: ='Consumer Model'!F25*Assumptions!$F$22*INDEX(Assumptions!$C$16:$G$16,1,'Consumer Model'!F$6) -> 0 | G23: ='Consumer Model'!G25*Assumptions!$F$22*INDEX(Assumptions!$C$16:$G$16,1,'Consumer Model'!G$6) -> 577.0332 | H23: ='Consumer Model'!H25*Assumptions!$F$22*INDEX(Assumptions!$C$16:$G$16,1,'Consumer Model'!H$6) -> 789.25586 | I23: ='Consumer Model'!I25*Assumptions!$F$22*INDEX(Assumptions!$C$16:$G$16,1,'Consumer Model'!I$6) -> 1079.5303 | J23: ='Consumer Model'!J25*Assumptions!$F$22*INDEX(Assumptions!$C$16:$G$16,1,'Consumer Model'!J$6) -> 1476.5625 | ... V23: ='Consumer Model'!V25*Assumptions!$F$22*INDEX(Assumptions!$C$16:$G$16,1,'Consumer Model'!V$6) -> 56250
B24: New invest users | C24: =C23 -> 0 | D24: =MAX(0,D23-C23) -> 0 | E24: =MAX(0,E23-D23) -> 0 | F24: =MAX(0,F23-E23) -> 0 | G24: =MAX(0,G23-F23) -> 577.0332 | H24: =MAX(0,H23-G23) -> 212.22266 | I24: =MAX(0,I23-H23) -> 290.27441 | J24: =MAX(0,J23-I23) -> 397.03223 | K24: =MAX(0,K23-J23) -> 2106.8895 | ... V24: =MAX(0,V23-U23) -> 8949.5766
B25: Opening AUM | C25: =0 -> 0 | D25: =C31 -> 0 | E25: =D31 -> 0 | F25: =E31 -> 0 | G25: =F31 -> 0 | H25: =G31 -> 958519.67 | I25: =H31 -> 1328675.1 | J25: =I31 -> 1833688.7 | K25: =J31 -> 2523251.8 | ... V25: =U31 -> 82967138
B26: + Initial rollovers | C26: =C24*Assumptions!$D$22*Assumptions!$H$22 -> 0 | D26: =D24*Assumptions!$D$22*Assumptions!$H$22 -> 0 | E26: =E24*Assumptions!$D$22*Assumptions!$H$22 -> 0 | F26: =F24*Assumptions!$D$22*Assumptions!$H$22 -> 0 | G26: =G24*Assumptions!$D$22*Assumptions!$H$22 -> 865549.8 | H26: =H24*Assumptions!$D$22*Assumptions!$H$22 -> 318333.98 | I26: =I24*Assumptions!$D$22*Assumptions!$H$22 -> 435411.62 | J26: =J24*Assumptions!$D$22*Assumptions!$H$22 -> 595548.35 | ... V26: =V24*Assumptions!$D$22*Assumptions!$H$22 -> 13424365
B27: + Contributions | C27: =C23*Assumptions!$D$22*Assumptions!$G$22*3 -> 0 | D27: =D23*Assumptions!$D$22*Assumptions!$G$22*3 -> 0 | E27: =E23*Assumptions!$D$22*Assumptions!$G$22*3 -> 0 | F27: =F23*Assumptions!$D$22*Assumptions!$G$22*3 -> 0 | G27: =G23*Assumptions!$D$22*Assumptions!$G$22*3 -> 86554.98 | H27: =H23*Assumptions!$D$22*Assumptions!$G$22*3 -> 118388.38 | I27: =I23*Assumptions!$D$22*Assumptions!$G$22*3 -> 161929.54 | J27: =J23*Assumptions!$D$22*Assumptions!$G$22*3 -> 221484.38 | ... V27: =V23*Assumptions!$D$22*Assumptions!$G$22*3 -> 8437500
B28: - Redemptions | C28: =-C25*Assumptions!$C$14/4 -> 0 | D28: =-D25*Assumptions!$C$14/4 -> 0 | E28: =-E25*Assumptions!$C$14/4 -> 0 | F28: =-F25*Assumptions!$C$14/4 -> 0 | G28: =-G25*Assumptions!$C$14/4 -> 0 | H28: =-H25*Assumptions!$C$14/4 -> -19170.393 | I28: =-I25*Assumptions!$C$14/4 -> -26573.501 | J28: =-J25*Assumptions!$C$14/4 -> -36673.774 | ... V28: =-V25*Assumptions!$C$14/4 -> -1659342.8
B29: - Churn leakage | C29: =-C25*(1-(1-Assumptions!$E$22)^3) -> 0 | D29: =-D25*(1-(1-Assumptions!$E$22)^3) -> 0 | E29: =-E25*(1-(1-Assumptions!$E$22)^3) -> 0 | F29: =-F25*(1-(1-Assumptions!$E$22)^3) -> 0 | G29: =-G25*(1-(1-Assumptions!$E$22)^3) -> 0 | H29: =-H25*(1-(1-Assumptions!$E$22)^3) -> -63255.244 | I29: =-I25*(1-(1-Assumptions!$E$22)^3) -> -87682.776 | J29: =-J25*(1-(1-Assumptions!$E$22)^3) -> -121009.96 | ... V29: =-V25*(1-(1-Assumptions!$E$22)^3) -> -5475220.5
B30: + Market return | C30: =(C25+(C26+C27)/2)*((1+Assumptions!$C$13)^(1/4)-1) -> 0 | D30: =(D25+(D26+D27)/2)*((1+Assumptions!$C$13)^(1/4)-1) -> 0 | E30: =(E25+(E26+E27)/2)*((1+Assumptions!$C$13)^(1/4)-1) -> 0 | F30: =(F25+(F26+F27)/2)*((1+Assumptions!$C$13)^(1/4)-1) -> 0 | G30: =(G25+(G26+G27)/2)*((1+Assumptions!$C$13)^(1/4)-1) -> 6414.889 | H30: =(H25+(H26+H27)/2)*((1+Assumptions!$C$13)^(1/4)-1) -> 15858.675 | I30: =(I25+(I26+I27)/2)*((1+Assumptions!$C$13)^(1/4)-1) -> 21928.766 | J30: =(J25+(J26+J27)/2)*((1+Assumptions!$C$13)^(1/4)-1) -> 30214.105 | ... V30: =(V25+(V26+V27)/2)*((1+Assumptions!$C$13)^(1/4)-1) -> 1265292.9
B31: CLOSING AUM | C31: =C25+C26+C27+C28+C29+C30 -> 0 | D31: =D25+D26+D27+D28+D29+D30 -> 0 | E31: =E25+E26+E27+E28+E29+E30 -> 0 | F31: =F25+F26+F27+F28+F29+F30 -> 0 | G31: =G25+G26+G27+G28+G29+G30 -> 958519.67 | H31: =H25+H26+H27+H28+H29+H30 -> 1328675.1 | I31: =I25+I26+I27+I28+I29+I30 -> 1833688.7 | J31: =J25+J26+J27+J28+J29+J30 -> 2523251.8 | ... V31: =V25+V26+V27+V28+V29+V30 -> 98959733
B32: Average AUM | C32: =(C25+C31)/2 -> 0 | D32: =(D25+D31)/2 -> 0 | E32: =(E25+E31)/2 -> 0 | F32: =(F25+F31)/2 -> 0 | G32: =(G25+G31)/2 -> 479259.83 | H32: =(H25+H31)/2 -> 1143597.4 | I32: =(I25+I31)/2 -> 1581181.9 | J32: =(J25+J31)/2 -> 2178470.3 | ... V32: =(V25+V31)/2 -> 90963435
B33: AUM per invest user | C33: =IF(C23=0,0,C31/C23) -> 0 | D33: =IF(D23=0,0,D31/D23) -> 0 | E33: =IF(E23=0,0,E31/E23) -> 0 | F33: =IF(F23=0,0,F31/F23) -> 0 | G33: =IF(G23=0,0,G31/G23) -> 1661.117 | H33: =IF(H23=0,0,H31/H23) -> 1683.4529 | I33: =IF(I23=0,0,I31/I23) -> 1698.5987 | J33: =IF(J23=0,0,J31/J23) -> 1708.8689 | ... V33: =IF(V23=0,0,V31/V23) -> 1759.2841
A35: SEGMENT 3 — Primary Bank Switcher
B36: Invest users (end of period) | C36: ='Consumer Model'!C26*Assumptions!$F$23*INDEX(Assumptions!$C$16:$G$16,1,'Consumer Model'!C$6) -> 0 | D36: ='Consumer Model'!D26*Assumptions!$F$23*INDEX(Assumptions!$C$16:$G$16,1,'Consumer Model'!D$6) -> 0 | E36: ='Consumer Model'!E26*Assumptions!$F$23*INDEX(Assumptions!$C$16:$G$16,1,'Consumer Model'!E$6) -> 0 | F36: ='Consumer Model'!F26*Assumptions!$F$23*INDEX(Assumptions!$C$16:$G$16,1,'Consumer Model'!F$6) -> 0 | G36: ='Consumer Model'!G26*Assumptions!$F$23*INDEX(Assumptions!$C$16:$G$16,1,'Consumer Model'!G$6) -> 184.65062 | H36: ='Consumer Model'!H26*Assumptions!$F$23*INDEX(Assumptions!$C$16:$G$16,1,'Consumer Model'!H$6) -> 252.56187 | I36: ='Consumer Model'!I26*Assumptions!$F$23*INDEX(Assumptions!$C$16:$G$16,1,'Consumer Model'!I$6) -> 345.44969 | J36: ='Consumer Model'!J26*Assumptions!$F$23*INDEX(Assumptions!$C$16:$G$16,1,'Consumer Model'!J$6) -> 472.5 | ... V36: ='Consumer Model'!V26*Assumptions!$F$23*INDEX(Assumptions!$C$16:$G$16,1,'Consumer Model'!V$6) -> 30000
B37: New invest users | C37: =C36 -> 0 | D37: =MAX(0,D36-C36) -> 0 | E37: =MAX(0,E36-D36) -> 0 | F37: =MAX(0,F36-E36) -> 0 | G37: =MAX(0,G36-F36) -> 184.65062 | H37: =MAX(0,H36-G36) -> 67.91125 | I37: =MAX(0,I36-H36) -> 92.887812 | J37: =MAX(0,J36-I36) -> 127.05031 | K37: =MAX(0,K36-J36) -> 1438.6744 | ... V37: =MAX(0,V36-U36) -> 4773.1075
B38: Opening AUM | C38: =0 -> 0 | D38: =C44 -> 0 | E38: =D44 -> 0 | F38: =E44 -> 0 | G38: =F44 -> 0 | H38: =G44 -> 849306.52 | I38: =H44 -> 1183926.3 | J38: =I44 -> 1640643.8 | K38: =J44 -> 2264406.6 | ... V38: =U44 -> 1.2591266e+08
B39: + Initial rollovers | C39: =C37*Assumptions!$D$23*Assumptions!$H$23 -> 0 | D39: =D37*Assumptions!$D$23*Assumptions!$H$23 -> 0 | E39: =E37*Assumptions!$D$23*Assumptions!$H$23 -> 0 | F39: =F37*Assumptions!$D$23*Assumptions!$H$23 -> 0 | G39: =G37*Assumptions!$D$23*Assumptions!$H$23 -> 784765.15 | H39: =H37*Assumptions!$D$23*Assumptions!$H$23 -> 288622.81 | I39: =I37*Assumptions!$D$23*Assumptions!$H$23 -> 394773.2 | J39: =J37*Assumptions!$D$23*Assumptions!$H$23 -> 539963.84 | ... V39: =V37*Assumptions!$D$23*Assumptions!$H$23 -> 20285707
B40: + Contributions | C40: =C36*Assumptions!$D$23*Assumptions!$G$23*3 -> 0 | D40: =D36*Assumptions!$D$23*Assumptions!$G$23*3 -> 0 | E40: =E36*Assumptions!$D$23*Assumptions!$G$23*3 -> 0 | F40: =F36*Assumptions!$D$23*Assumptions!$G$23*3 -> 0 | G40: =G36*Assumptions!$D$23*Assumptions!$G$23*3 -> 58857.386 | H40: =H36*Assumptions!$D$23*Assumptions!$G$23*3 -> 80504.097 | I40: =I36*Assumptions!$D$23*Assumptions!$G$23*3 -> 110112.09 | J40: =J36*Assumptions!$D$23*Assumptions!$G$23*3 -> 150609.38 | ... V40: =V36*Assumptions!$D$23*Assumptions!$G$23*3 -> 9562500
B41: - Redemptions | C41: =-C38*Assumptions!$C$14/4 -> 0 | D41: =-D38*Assumptions!$C$14/4 -> 0 | E41: =-E38*Assumptions!$C$14/4 -> 0 | F41: =-F38*Assumptions!$C$14/4 -> 0 | G41: =-G38*Assumptions!$C$14/4 -> 0 | H41: =-H38*Assumptions!$C$14/4 -> -16986.13 | I41: =-I38*Assumptions!$C$14/4 -> -23678.527 | J41: =-J38*Assumptions!$C$14/4 -> -32812.877 | ... V41: =-V38*Assumptions!$C$14/4 -> -2518253.1
B42: - Churn leakage | C42: =-C38*(1-(1-Assumptions!$E$23)^3) -> 0 | D42: =-D38*(1-(1-Assumptions!$E$23)^3) -> 0 | E42: =-E38*(1-(1-Assumptions!$E$23)^3) -> 0 | F42: =-F38*(1-(1-Assumptions!$E$23)^3) -> 0 | G42: =-G38*(1-(1-Assumptions!$E$23)^3) -> 0 | H42: =-H38*(1-(1-Assumptions!$E$23)^3) -> -31452.541 | I42: =-I38*(1-(1-Assumptions!$E$23)^3) -> -43844.584 | J42: =-J38*(1-(1-Assumptions!$E$23)^3) -> -60758.296 | ... V42: =-V38*(1-(1-Assumptions!$E$23)^3) -> -4662949
B43: + Market return | C43: =(C38+(C39+C40)/2)*((1+Assumptions!$C$13)^(1/4)-1) -> 0 | D43: =(D38+(D39+D40)/2)*((1+Assumptions!$C$13)^(1/4)-1) -> 0 | E43: =(E38+(E39+E40)/2)*((1+Assumptions!$C$13)^(1/4)-1) -> 0 | F43: =(F38+(F39+F40)/2)*((1+Assumptions!$C$13)^(1/4)-1) -> 0 | G43: =(G38+(G39+G40)/2)*((1+Assumptions!$C$13)^(1/4)-1) -> 5683.9804 | H43: =(H38+(H39+H40)/2)*((1+Assumptions!$C$13)^(1/4)-1) -> 13931.578 | I43: =(I38+(I39+I40)/2)*((1+Assumptions!$C$13)^(1/4)-1) -> 19355.323 | J43: =(J38+(J39+J40)/2)*((1+Assumptions!$C$13)^(1/4)-1) -> 26760.759 | ... V43: =(V38+(V39+V40)/2)*((1+Assumptions!$C$13)^(1/4)-1) -> 1897799.9
B44: CLOSING AUM | C44: =C38+C39+C40+C41+C42+C43 -> 0 | D44: =D38+D39+D40+D41+D42+D43 -> 0 | E44: =E38+E39+E40+E41+E42+E43 -> 0 | F44: =F38+F39+F40+F41+F42+F43 -> 0 | G44: =G38+G39+G40+G41+G42+G43 -> 849306.52 | H44: =H38+H39+H40+H41+H42+H43 -> 1183926.3 | I44: =I38+I39+I40+I41+I42+I43 -> 1640643.8 | J44: =J38+J39+J40+J41+J42+J43 -> 2264406.6 | ... V44: =V38+V39+V40+V41+V42+V43 -> 1.5047746e+08
B45: Average AUM | C45: =(C38+C44)/2 -> 0 | D45: =(D38+D44)/2 -> 0 | E45: =(E38+E44)/2 -> 0 | F45: =(F38+F44)/2 -> 0 | G45: =(G38+G44)/2 -> 424653.26 | H45: =(H38+H44)/2 -> 1016616.4 | I45: =(I38+I44)/2 -> 1412285.1 | J45: =(J38+J44)/2 -> 1952525.2 | ... V45: =(V38+V44)/2 -> 1.3819506e+08
B46: AUM per invest user | C46: =IF(C36=0,0,C44/C36) -> 0 | D46: =IF(D36=0,0,D44/D36) -> 0 | E46: =IF(E36=0,0,E44/E36) -> 0 | F46: =IF(F36=0,0,F44/F36) -> 0 | G46: =IF(G36=0,0,G44/G36) -> 4599.5324 | H46: =IF(H36=0,0,H44/H36) -> 4687.6685 | I46: =IF(I36=0,0,I44/I36) -> 4749.299 | J46: =IF(J36=0,0,J44/J36) -> 4792.395 | ... V46: =IF(V36=0,0,V44/V36) -> 5015.9154
A48: SEGMENT 4 — Crypto-Curious Investor
B49: Invest users (end of period) | C49: ='Consumer Model'!C27*Assumptions!$F$24*INDEX(Assumptions!$C$16:$G$16,1,'Consumer Model'!C$6) -> 0 | D49: ='Consumer Model'!D27*Assumptions!$F$24*INDEX(Assumptions!$C$16:$G$16,1,'Consumer Model'!D$6) -> 0 | E49: ='Consumer Model'!E27*Assumptions!$F$24*INDEX(Assumptions!$C$16:$G$16,1,'Consumer Model'!E$6) -> 0 | F49: ='Consumer Model'!F27*Assumptions!$F$24*INDEX(Assumptions!$C$16:$G$16,1,'Consumer Model'!F$6) -> 0 | G49: ='Consumer Model'!G27*Assumptions!$F$24*INDEX(Assumptions!$C$16:$G$16,1,'Consumer Model'!G$6) -> 323.13859 | H49: ='Consumer Model'!H27*Assumptions!$F$24*INDEX(Assumptions!$C$16:$G$16,1,'Consumer Model'!H$6) -> 441.98328 | I49: ='Consumer Model'!I27*Assumptions!$F$24*INDEX(Assumptions!$C$16:$G$16,1,'Consumer Model'!I$6) -> 604.53695 | J49: ='Consumer Model'!J27*Assumptions!$F$24*INDEX(Assumptions!$C$16:$G$16,1,'Consumer Model'!J$6) -> 826.875 | ... V49: ='Consumer Model'!V27*Assumptions!$F$24*INDEX(Assumptions!$C$16:$G$16,1,'Consumer Model'!V$6) -> 17500
B50: New invest users | C50: =C49 -> 0 | D50: =MAX(0,D49-C49) -> 0 | E50: =MAX(0,E49-D49) -> 0 | F50: =MAX(0,F49-E49) -> 0 | G50: =MAX(0,G49-F49) -> 323.13859 | H50: =MAX(0,H49-G49) -> 118.84469 | I50: =MAX(0,I49-H49) -> 162.55367 | J50: =MAX(0,J49-I49) -> 222.33805 | K50: =MAX(0,K49-J49) -> 287.97674 | ... V50: =MAX(0,V49-U49) -> 2784.3127
B51: Opening AUM | C51: =0 -> 0 | D51: =C57 -> 0 | E51: =D57 -> 0 | F51: =E57 -> 0 | G51: =F57 -> 0 | H51: =G57 -> 4108738.1 | I51: =H57 -> 5615866.1 | J51: =I57 -> 7677492.4 | K51: =J57 -> 10497541 | ... V51: =U57 -> 1.8652093e+08
B52: + Initial rollovers | C52: =C50*Assumptions!$D$24*Assumptions!$H$24 -> 0 | D52: =D50*Assumptions!$D$24*Assumptions!$H$24 -> 0 | E52: =E50*Assumptions!$D$24*Assumptions!$H$24 -> 0 | F52: =F50*Assumptions!$D$24*Assumptions!$H$24 -> 0 | G52: =G50*Assumptions!$D$24*Assumptions!$H$24 -> 3877663.1 | H52: =H50*Assumptions!$D$24*Assumptions!$H$24 -> 1426136.2 | I52: =I50*Assumptions!$D$24*Assumptions!$H$24 -> 1950644.1 | J52: =J50*Assumptions!$D$24*Assumptions!$H$24 -> 2668056.6 | ... V52: =V50*Assumptions!$D$24*Assumptions!$H$24 -> 33411753
B53: + Contributions | C53: =C49*Assumptions!$D$24*Assumptions!$G$24*3 -> 0 | D53: =D49*Assumptions!$D$24*Assumptions!$G$24*3 -> 0 | E53: =E49*Assumptions!$D$24*Assumptions!$G$24*3 -> 0 | F53: =F49*Assumptions!$D$24*Assumptions!$G$24*3 -> 0 | G53: =G49*Assumptions!$D$24*Assumptions!$G$24*3 -> 203577.31 | H53: =H49*Assumptions!$D$24*Assumptions!$G$24*3 -> 278449.47 | I53: =I49*Assumptions!$D$24*Assumptions!$G$24*3 -> 380858.28 | J53: =J49*Assumptions!$D$24*Assumptions!$G$24*3 -> 520931.25 | ... V53: =V49*Assumptions!$D$24*Assumptions!$G$24*3 -> 11025000
B54: - Redemptions | C54: =-C51*Assumptions!$C$14/4 -> 0 | D54: =-D51*Assumptions!$C$14/4 -> 0 | E54: =-E51*Assumptions!$C$14/4 -> 0 | F54: =-F51*Assumptions!$C$14/4 -> 0 | G54: =-G51*Assumptions!$C$14/4 -> 0 | H54: =-H51*Assumptions!$C$14/4 -> -82174.763 | I54: =-I51*Assumptions!$C$14/4 -> -112317.32 | J54: =-J51*Assumptions!$C$14/4 -> -153549.85 | ... V54: =-V51*Assumptions!$C$14/4 -> -3730418.6
B55: - Churn leakage | C55: =-C51*(1-(1-Assumptions!$E$24)^3) -> 0 | D55: =-D51*(1-(1-Assumptions!$E$24)^3) -> 0 | E55: =-E51*(1-(1-Assumptions!$E$24)^3) -> 0 | F55: =-F51*(1-(1-Assumptions!$E$24)^3) -> 0 | G55: =-G51*(1-(1-Assumptions!$E$24)^3) -> 0 | H55: =-H51*(1-(1-Assumptions!$E$24)^3) -> -182133.68 | I55: =-I51*(1-(1-Assumptions!$E$24)^3) -> -248942.22 | J55: =-J51*(1-(1-Assumptions!$E$24)^3) -> -340330.76 | ... V55: =-V51*(1-(1-Assumptions!$E$24)^3) -> -8268169.8
B56: + Market return | C56: =(C51+(C52+C53)/2)*((1+Assumptions!$C$13)^(1/4)-1) -> 0 | D56: =(D51+(D52+D53)/2)*((1+Assumptions!$C$13)^(1/4)-1) -> 0 | E56: =(E51+(E52+E53)/2)*((1+Assumptions!$C$13)^(1/4)-1) -> 0 | F56: =(F51+(F52+F53)/2)*((1+Assumptions!$C$13)^(1/4)-1) -> 0 | G56: =(G51+(G52+G53)/2)*((1+Assumptions!$C$13)^(1/4)-1) -> 27497.713 | H56: =(H51+(H52+H53)/2)*((1+Assumptions!$C$13)^(1/4)-1) -> 66850.758 | I56: =(I51+(I52+I53)/2)*((1+Assumptions!$C$13)^(1/4)-1) -> 91383.476 | J56: =(J51+(J52+J53)/2)*((1+Assumptions!$C$13)^(1/4)-1) -> 124941.63 | ... V56: =(V51+(V52+V53)/2)*((1+Assumptions!$C$13)^(1/4)-1) -> 2812798.6
B57: CLOSING AUM | C57: =C51+C52+C53+C54+C55+C56 -> 0 | D57: =D51+D52+D53+D54+D55+D56 -> 0 | E57: =E51+E52+E53+E54+E55+E56 -> 0 | F57: =F51+F52+F53+F54+F55+F56 -> 0 | G57: =G51+G52+G53+G54+G55+G56 -> 4108738.1 | H57: =H51+H52+H53+H54+H55+H56 -> 5615866.1 | I57: =I51+I52+I53+I54+I55+I56 -> 7677492.4 | J57: =J51+J52+J53+J54+J55+J56 -> 10497541 | ... V57: =V51+V52+V53+V54+V55+V56 -> 2.2177189e+08
B58: Average AUM | C58: =(C51+C57)/2 -> 0 | D58: =(D51+D57)/2 -> 0 | E58: =(E51+E57)/2 -> 0 | F58: =(F51+F57)/2 -> 0 | G58: =(G51+G57)/2 -> 2054369.1 | H58: =(H51+H57)/2 -> 4862302.1 | I58: =(I51+I57)/2 -> 6646679.3 | J58: =(J51+J57)/2 -> 9087516.8 | ... V58: =(V51+V57)/2 -> 2.0414641e+08
B59: AUM per invest user | C59: =IF(C49=0,0,C57/C49) -> 0 | D59: =IF(D49=0,0,D57/D49) -> 0 | E59: =IF(E49=0,0,E57/E49) -> 0 | F59: =IF(F49=0,0,F57/F49) -> 0 | G59: =IF(G49=0,0,G57/G49) -> 12715.096 | H59: =IF(H49=0,0,H57/H49) -> 12706.06 | I59: =IF(I49=0,0,I57/I49) -> 12699.79 | J59: =IF(J49=0,0,J57/J49) -> 12695.439 | ... V59: =IF(V49=0,0,V57/V49) -> 12672.68
A61: TOTAL — ALL SEGMENTS
B62: Total invest users | C62: =C10+C23+C36+C49 -> 0 | D62: =D10+D23+D36+D49 -> 0 | E62: =E10+E23+E36+E49 -> 0 | F62: =F10+F23+F36+F49 -> 0 | G62: =G10+G23+G36+G49 -> 1318.7132 | H62: =H10+H23+H36+H49 -> 1803.7127 | I62: =I10+I23+I36+I49 -> 2467.0865 | J62: =J10+J23+J36+J49 -> 3374.4375 | ... V62: =V10+V23+V36+V49 -> 117750
B63: Initial rollovers | C63: =C13+C26+C39+C52 -> 0 | D63: =D13+D26+D39+D52 -> 0 | E63: =E13+E26+E39+E52 -> 0 | F63: =F13+F26+F39+F52 -> 0 | G63: =G13+G26+G39+G52 -> 5580603.5 | H63: =H13+H26+H39+H52 -> 2052447.7 | I63: =I13+I26+I39+I52 -> 2807301.9 | J63: =J13+J26+J39+J52 -> 3839778.1 | ... V63: =V13+V26+V39+V52 -> 67623001
B64: Contributions | C64: =C14+C27+C40+C53 -> 0 | D64: =D14+D27+D40+D53 -> 0 | E64: =E14+E27+E40+E53 -> 0 | F64: =F14+F27+F40+F53 -> 0 | G64: =G14+G27+G40+G53 -> 355304.73 | H64: =H14+H27+H40+H53 -> 485979.56 | I64: =I14+I27+I40+I53 -> 664714.29 | J64: =J14+J27+J40+J53 -> 909184.5 | ... V64: =V14+V27+V40+V53 -> 29403000
B65: Redemptions | C65: =C15+C28+C41+C54 -> 0 | D65: =D15+D28+D41+D54 -> 0 | E65: =E15+E28+E41+E54 -> 0 | F65: =F15+F28+F41+F54 -> 0 | G65: =G15+G28+G41+G54 -> 0 | H65: =H15+H28+H41+H54 -> -119518.04 | I65: =I15+I28+I41+I54 -> -164199.99 | J65: =J15+J28+J41+J54 -> -225273.53 | ... V65: =V15+V28+V41+V54 -> -7968815.9
B66: Churn leakage | C66: =C16+C29+C42+C55 -> 0 | D66: =D16+D29+D42+D55 -> 0 | E66: =E16+E29+E42+E55 -> 0 | F66: =F16+F29+F42+F55 -> 0 | G66: =G16+G29+G42+G55 -> 0 | H66: =H16+H29+H42+H55 -> -282440.9 | I66: =I16+I29+I42+I55 -> -388163.39 | J66: =J16+J29+J42+J55 -> -532653.95 | ... V66: =V16+V29+V42+V55 -> -18693217
B67: Market return | C67: =C17+C30+C43+C56 -> 0 | D67: =D17+D30+D43+D56 -> 0 | E67: =E17+E30+E43+E56 -> 0 | F67: =F17+F30+F43+F56 -> 0 | G67: =G17+G30+G43+G56 -> 39993.699 | H67: =H17+H30+H43+H56 -> 97629.196 | I67: =I17+I30+I43+I56 -> 134024.19 | J67: =J17+J30+J43+J56 -> 183776.56 | ... V67: =V17+V30+V43+V56 -> 6022780.4
B68: TOTAL CLOSING AUM | C68: =C18+C31+C44+C57 -> 0 | D68: =D18+D31+D44+D57 -> 0 | E68: =E18+E31+E44+E57 -> 0 | F68: =F18+F31+F44+F57 -> 0 | G68: =G18+G31+G44+G57 -> 5975901.9 | H68: =H18+H31+H44+H57 -> 8209999.5 | I68: =I18+I31+I44+I57 -> 11263676 | J68: =J18+J31+J44+J57 -> 15438488 | ... V68: =V18+V31+V44+V57 -> 4.7482754e+08
B69: Total average AUM | C69: =C19+C32+C45+C58 -> 0 | D69: =D19+D32+D45+D58 -> 0 | E69: =E19+E32+E45+E58 -> 0 | F69: =F19+F32+F45+F58 -> 0 | G69: =G19+G32+G45+G58 -> 2987951 | H69: =H19+H32+H45+H58 -> 7092950.7 | I69: =I19+I32+I45+I58 -> 9736838 | J69: =J19+J32+J45+J58 -> 13351082 | ... V69: =V19+V32+V45+V58 -> 4.3663417e+08
B70: AUM per invest user | C70: =IF(C62=0,0,C68/C62) -> 0 | D70: =IF(D62=0,0,D68/D62) -> 0 | E70: =IF(E62=0,0,E68/E62) -> 0 | F70: =IF(F62=0,0,F68/F62) -> 0 | G70: =IF(G62=0,0,G68/G62) -> 4531.616 | H70: =IF(H62=0,0,H68/H62) -> 4551.7224 | I70: =IF(I62=0,0,I68/I62) -> 4565.5782 | J70: =IF(J62=0,0,J68/J62) -> 4575.1294 | ... V70: =IF(V62=0,0,V68/V62) -> 4032.5057
B71: Effective adoption (% of actives) | C71: =C62/'Consumer Model'!C12 -> 0 | D71: =D62/'Consumer Model'!D12 -> 0 | E71: =E62/'Consumer Model'!E12 -> 0 | F71: =F62/'Consumer Model'!F12 -> 0 | G71: =G62/'Consumer Model'!G12 -> 0.0964125 | H71: =H62/'Consumer Model'!H12 -> 0.0964125 | I71: =I62/'Consumer Model'!I12 -> 0.0964125 | J71: =J62/'Consumer Model'!J12 -> 0.0964125 | ... V71: =V62/'Consumer Model'!V12 -> 0.2355
A73: AUM FEE REVENUE
B74: AUM fee revenue (quarter) | C74: =C69*Assumptions!$C$12/4 -> 0 | D74: =D69*Assumptions!$C$12/4 -> 0 | E74: =E69*Assumptions!$C$12/4 -> 0 | F74: =F69*Assumptions!$C$12/4 -> 0 | G74: =G69*Assumptions!$C$12/4 -> 3734.9387 | H74: =H69*Assumptions!$C$12/4 -> 8866.1884 | I74: =I69*Assumptions!$C$12/4 -> 12171.047 | J74: =J69*Assumptions!$C$12/4 -> 16688.853 | ... V74: =V69*Assumptions!$C$12/4 -> 545792.71
B75: AUM fee (annual run-rate) | C75: =C68*Assumptions!$C$12 -> 0 | D75: =D68*Assumptions!$C$12 -> 0 | E75: =E68*Assumptions!$C$12 -> 0 | F75: =F68*Assumptions!$C$12 -> 0 | G75: =G68*Assumptions!$C$12 -> 29879.51 | H75: =H68*Assumptions!$C$12 -> 41049.997 | I75: =I68*Assumptions!$C$12 -> 56318.382 | J75: =J68*Assumptions!$C$12 -> 77192.441 | ... V75: =V68*Assumptions!$C$12 -> 2374137.7

Sheet Revenue Comparison
A1: REVENUE COMPARISON — does AUM overtake the T-bill sleeve?
A2: Compared on what Vaulta KEEPS. T-bill contributes only the 20% sleeve; the 80% consumer reward is passed through and is not Vaulta revenue.
B5: Quarter | C5: 1 | D5: 2 | E5: 3 | F5: 4 | G5: 5 | H5: 6 | I5: 7 | J5: 8 | K5: 9 | L5: 10 | M5: 11 | N5: 12 | O5: 13 | P5: 14 | Q5: 15 | R5: 16 | S5: 17 | T5: 18 | U5: 19 | V5: 20
B6: Year | C6: =INT((C5-1)/4)+1 -> 1 | D6: =INT((D5-1)/4)+1 -> 1 | E6: =INT((E5-1)/4)+1 -> 1 | F6: =INT((F5-1)/4)+1 -> 1 | G6: =INT((G5-1)/4)+1 -> 2 | H6: =INT((H5-1)/4)+1 -> 2 | I6: =INT((I5-1)/4)+1 -> 2 | J6: =INT((J5-1)/4)+1 -> 2 | ... V6: =INT((V5-1)/4)+1 -> 5
B7: Period | C7: 2027 Q1 | D7: 2027 Q2 | E7: 2027 Q3 | F7: 2027 Q4 | G7: 2028 Q1 | H7: 2028 Q2 | I7: 2028 Q3 | J7: 2028 Q4 | K7: 2029 Q1 | L7: 2029 Q2 | M7: 2029 Q3 | N7: 2029 Q4 | O7: 2030 Q1 | P7: 2030 Q2 | Q7: 2030 Q3 | R7: 2030 Q4 | S7: 2031 Q1 | T7: 2031 Q2 | U7: 2031 Q3 | V7: 2031 Q4
A9: VAULTA RETAINED REVENUE BY LINE
B10: Total wallet balances (avg) | C10: ='Consumer Model'!C19 -> 2625474 | D10: ='Consumer Model'!D19 -> 4668826.4 | E10: ='Consumer Model'!E19 -> 8302477.9 | F10: ='Consumer Model'!F19 -> 14764126 | G10: ='Consumer Model'!G19 -> 25261278 | H10: ='Consumer Model'!H19 -> 34551932 | I10: ='Consumer Model'!I19 -> 47259525 | J10: ='Consumer Model'!J19 -> 64640746 | ... V10: ='Consumer Model'!V19 -> 1.0941828e+09
B11: T-bill gross income | C11: =C10*Assumptions!$C$5/4 -> 31505.689 | D11: =D10*Assumptions!$C$5/4 -> 56025.917 | E11: =E10*Assumptions!$C$5/4 -> 99629.735 | F11: =F10*Assumptions!$C$5/4 -> 177169.51 | G11: =G10*Assumptions!$C$5/4 -> 303135.34 | H11: =H10*Assumptions!$C$5/4 -> 414623.19 | I11: =I10*Assumptions!$C$5/4 -> 567114.3 | J11: =J10*Assumptions!$C$5/4 -> 775688.95 | ... V11: =V10*Assumptions!$C$5/4 -> 13130194
B12: less consumer reward (80%) | C12: =-C11*Assumptions!$C$7 -> -25204.551 | D12: =-D11*Assumptions!$C$7 -> -44820.734 | E12: =-E11*Assumptions!$C$7 -> -79703.788 | F12: =-F11*Assumptions!$C$7 -> -141735.61 | G12: =-G11*Assumptions!$C$7 -> -242508.27 | H12: =-H11*Assumptions!$C$7 -> -331698.55 | I12: =-I11*Assumptions!$C$7 -> -453691.44 | J12: =-J11*Assumptions!$C$7 -> -620551.16 | ... V12: =-V11*Assumptions!$C$7 -> -10504155
B13: T-BILL NIM (Vaulta keeps) | C13: =C11*Assumptions!$C$6 -> 6301.1377 | D13: =D11*Assumptions!$C$6 -> 11205.183 | E13: =E11*Assumptions!$C$6 -> 19925.947 | F13: =F11*Assumptions!$C$6 -> 35433.901 | G13: =G11*Assumptions!$C$6 -> 60627.068 | H13: =H11*Assumptions!$C$6 -> 82924.637 | I13: =I11*Assumptions!$C$6 -> 113422.86 | J13: =J11*Assumptions!$C$6 -> 155137.79 | ... V13: =V11*Assumptions!$C$6 -> 2626038.7
B14: memo: consumer spend | C14: =C10*Assumptions!$C$47*3 -> 1575284.4 | D14: =D10*Assumptions!$C$47*3 -> 2801295.9 | E14: =E10*Assumptions!$C$47*3 -> 4981486.7 | F14: =F10*Assumptions!$C$47*3 -> 8858475.3 | G14: =G10*Assumptions!$C$47*3 -> 15156767 | H14: =H10*Assumptions!$C$47*3 -> 20731159 | I14: =I10*Assumptions!$C$47*3 -> 28355715 | J14: =J10*Assumptions!$C$47*3 -> 38784448 | ... V14: =V10*Assumptions!$C$47*3 -> 6.5650968e+08
B15: QR merchant fees | C15: =C14*Assumptions!$C$48*Assumptions!$C$50 -> 3150.5689 | D15: =D14*Assumptions!$C$48*Assumptions!$C$50 -> 5602.5917 | E15: =E14*Assumptions!$C$48*Assumptions!$C$50 -> 9962.9735 | F15: =F14*Assumptions!$C$48*Assumptions!$C$50 -> 17716.951 | G15: =G14*Assumptions!$C$48*Assumptions!$C$50 -> 30313.534 | H15: =H14*Assumptions!$C$48*Assumptions!$C$50 -> 41462.319 | I15: =I14*Assumptions!$C$48*Assumptions!$C$50 -> 56711.43 | J15: =J14*Assumptions!$C$48*Assumptions!$C$50 -> 77568.895 | ... V15: =V14*Assumptions!$C$48*Assumptions!$C$50 -> 1313019.4
B16: Rain interchange (net of txn cost) | C16: =C14*Assumptions!$C$49*Assumptions!$C$51-C14*Assumptions!$C$49/Assumptions!$C$53*Assumptions!$C$52 -> 157.52844 | D16: =D14*Assumptions!$C$49*Assumptions!$C$51-D14*Assumptions!$C$49/Assumptions!$C$53*Assumptions!$C$52 -> 280.12959 | E16: =E14*Assumptions!$C$49*Assumptions!$C$51-E14*Assumptions!$C$49/Assumptions!$C$53*Assumptions!$C$52 -> 498.14867 | F16: =F14*Assumptions!$C$49*Assumptions!$C$51-F14*Assumptions!$C$49/Assumptions!$C$53*Assumptions!$C$52 -> 885.84753 | G16: =G14*Assumptions!$C$49*Assumptions!$C$51-G14*Assumptions!$C$49/Assumptions!$C$53*Assumptions!$C$52 -> 1515.6767 | H16: =H14*Assumptions!$C$49*Assumptions!$C$51-H14*Assumptions!$C$49/Assumptions!$C$53*Assumptions!$C$52 -> 2073.1159 | I16: =I14*Assumptions!$C$49*Assumptions!$C$51-I14*Assumptions!$C$49/Assumptions!$C$53*Assumptions!$C$52 -> 2835.5715 | J16: =J14*Assumptions!$C$49*Assumptions!$C$51-J14*Assumptions!$C$49/Assumptions!$C$53*Assumptions!$C$52 -> 3878.4448 | ... V16: =V14*Assumptions!$C$49*Assumptions!$C$51-V14*Assumptions!$C$49/Assumptions!$C$53*Assumptions!$C$52 -> 65650.968
B17: Transaction fees (QR + card net) | C17: =C15+C16 -> 3308.0973 | D17: =D15+D16 -> 5882.7213 | E17: =E15+E16 -> 10461.122 | F17: =F15+F16 -> 18602.798 | G17: =G15+G16 -> 31829.211 | H17: =H15+H16 -> 43535.434 | I17: =I15+I16 -> 59547.001 | J17: =J15+J16 -> 81447.34 | ... V17: =V15+V16 -> 1378670.3
B18: AUM FEE | C18: ='AUM Engine'!C74 -> 0 | D18: ='AUM Engine'!D74 -> 0 | E18: ='AUM Engine'!E74 -> 0 | F18: ='AUM Engine'!F74 -> 0 | G18: ='AUM Engine'!G74 -> 3734.9387 | H18: ='AUM Engine'!H74 -> 8866.1884 | I18: ='AUM Engine'!I74 -> 12171.047 | J18: ='AUM Engine'!J74 -> 16688.853 | ... V18: ='AUM Engine'!V74 -> 545792.71
B19: TOTAL VAULTA REVENUE (retained) | C19: =C13+C17+C18 -> 9609.235 | D19: =D13+D17+D18 -> 17087.905 | E19: =E13+E17+E18 -> 30387.069 | F19: =F13+F17+F18 -> 54036.699 | G19: =G13+G17+G18 -> 96191.218 | H19: =H13+H17+H18 -> 135326.26 | I19: =I13+I17+I18 -> 185140.91 | J19: =J13+J17+J18 -> 253273.98 | ... V19: =V13+V17+V18 -> 4550501.8
A21: MIX
B22: T-bill NIM % | C22: =C13/C19 -> 0.6557377 | D22: =D13/D19 -> 0.6557377 | E22: =E13/E19 -> 0.6557377 | F22: =F13/F19 -> 0.6557377 | G22: =G13/G19 -> 0.63027654 | H22: =H13/H19 -> 0.61277565 | I22: =I13/I19 -> 0.61262992 | J22: =J13/J19 -> 0.61252952 | ... V22: =V13/V19 -> 0.57708773
B23: Transaction fees % | C23: =C17/C19 -> 0.3442623 | D23: =D17/D19 -> 0.3442623 | E23: =E17/E19 -> 0.3442623 | F23: =F17/F19 -> 0.3442623 | G23: =G17/G19 -> 0.33089519 | H23: =H17/H19 -> 0.32170722 | I23: =I17/I19 -> 0.32163071 | J23: =J17/J19 -> 0.321578 | ... V23: =V17/V19 -> 0.30297106
B24: AUM fee % | C24: =C18/C19 -> 0 | D24: =D18/D19 -> 0 | E24: =E18/E19 -> 0 | F24: =F18/F19 -> 0 | G24: =G18/G19 -> 0.038828271 | H24: =H18/H19 -> 0.065517132 | I24: =I18/I19 -> 0.065739375 | J24: =J18/J19 -> 0.065892488 | ... V24: =V18/V19 -> 0.11994121
A26: THE TEST — AUM vs NIM
B27: AUM fee / T-bill NIM | C27: =IF(C13=0,0,C18/C13) -> 0 | D27: =IF(D13=0,0,D18/D13) -> 0 | E27: =IF(E13=0,0,E18/E13) -> 0 | F27: =IF(F13=0,0,F18/F13) -> 0 | G27: =IF(G13=0,0,G18/G13) -> 0.061605134 | H27: =IF(H13=0,0,H18/H13) -> 0.10691863 | I27: =IF(I13=0,0,I18/I13) -> 0.10730683 | J27: =IF(J13=0,0,J18/J13) -> 0.10757439 | ... V27: =IF(V13=0,0,V18/V13) -> 0.20783879
B28: AUM overtakes NIM? | C28: =IF(C18>C13,"YES","no") -> no | D28: =IF(D18>D13,"YES","no") -> no | E28: =IF(E18>E13,"YES","no") -> no | F28: =IF(F18>F13,"YES","no") -> no | G28: =IF(G18>G13,"YES","no") -> no | H28: =IF(H18>H13,"YES","no") -> no | I28: =IF(I18>I13,"YES","no") -> no | J28: =IF(J18>J13,"YES","no") -> no | ... V28: =IF(V18>V13,"YES","no") -> no
A30: ANNUAL SUMMARY
B31: Annual | C31: Year 1 | D31: Year 2 | E31: Year 3 | F31: Year 4 | G31: Year 5
B32: T-bill NIM (Vaulta keeps) | C32: =SUMIF('Consumer Model'!$C$6:$V$6,1,$C$13:$V$13) -> 72866.169 | D32: =SUMIF('Consumer Model'!$C$6:$V$6,2,$C$13:$V$13) -> 412112.35 | E32: =SUMIF('Consumer Model'!$C$6:$V$6,3,$C$13:$V$13) -> 1421256.2 | F32: =SUMIF('Consumer Model'!$C$6:$V$6,4,$C$13:$V$13) -> 3752693 | G32: =SUMIF('Consumer Model'!$C$6:$V$6,5,$C$13:$V$13) -> 8252607.1
B33: Transaction fees | C33: =SUMIF('Consumer Model'!$C$6:$V$6,1,$C$17:$V$17) -> 38254.739 | D33: =SUMIF('Consumer Model'!$C$6:$V$6,2,$C$17:$V$17) -> 216358.99 | E33: =SUMIF('Consumer Model'!$C$6:$V$6,3,$C$17:$V$17) -> 746159.52 | F33: =SUMIF('Consumer Model'!$C$6:$V$6,4,$C$17:$V$17) -> 1970163.8 | G33: =SUMIF('Consumer Model'!$C$6:$V$6,5,$C$17:$V$17) -> 4332618.7
B34: AUM fee | C34: =SUMIF('Consumer Model'!$C$6:$V$6,1,$C$18:$V$18) -> 0 | D34: =SUMIF('Consumer Model'!$C$6:$V$6,2,$C$18:$V$18) -> 41461.027 | E34: =SUMIF('Consumer Model'!$C$6:$V$6,3,$C$18:$V$18) -> 198105.01 | F34: =SUMIF('Consumer Model'!$C$6:$V$6,4,$C$18:$V$18) -> 682297.66 | G34: =SUMIF('Consumer Model'!$C$6:$V$6,5,$C$18:$V$18) -> 1695038.8
B35: Total retained revenue | C35: =SUMIF('Consumer Model'!$C$6:$V$6,1,$C$19:$V$19) -> 111120.91 | D35: =SUMIF('Consumer Model'!$C$6:$V$6,2,$C$19:$V$19) -> 669932.37 | E35: =SUMIF('Consumer Model'!$C$6:$V$6,3,$C$19:$V$19) -> 2365520.8 | F35: =SUMIF('Consumer Model'!$C$6:$V$6,4,$C$19:$V$19) -> 6405154.5 | G35: =SUMIF('Consumer Model'!$C$6:$V$6,5,$C$19:$V$19) -> 14280265
B36: AUM as % of retained revenue | C36: =C34/C35 -> 0 | D36: =D34/D35 -> 0.061888378 | E36: =E34/E35 -> 0.08374689 | F36: =F34/F35 -> 0.10652322 | G36: =G34/G35 -> 0.118698
B37: AUM / NIM ratio | C37: =C34/C32 -> 0 | D37: =D34/D32 -> 0.10060613 | E37: =E34/E32 -> 0.13938726 | F37: =F34/F32 -> 0.18181547 | G37: =G34/G32 -> 0.20539435
B38: AUM overtakes NIM? | C38: =IF(C34>C32,"YES","no") -> no | D38: =IF(D34>D32,"YES","no") -> no | E38: =IF(E34>E32,"YES","no") -> no | F38: =IF(F34>F32,"YES","no") -> no | G38: =IF(G34>G32,"YES","no") -> no
B39: memo: closing AUM (year end) | C39: =INDEX('AUM Engine'!$C$68:$V$68,1,4) -> 0 | D39: =INDEX('AUM Engine'!$C$68:$V$68,1,8) -> 15438488 | E39: =INDEX('AUM Engine'!$C$68:$V$68,1,12) -> 65492944 | F39: =INDEX('AUM Engine'!$C$68:$V$68,1,16) -> 2.1191114e+08 | G39: =INDEX('AUM Engine'!$C$68:$V$68,1,20) -> 4.7482754e+08
B40: memo: total wallet balances (year end) | C40: =INDEX('Consumer Model'!$C$20:$V$20,1,4) -> 18900000 | D40: =INDEX('Consumer Model'!$C$20:$V$20,1,8) -> 74681250 | E40: =INDEX('Consumer Model'!$C$20:$V$20,1,12) -> 237750000 | F40: =INDEX('Consumer Model'!$C$20:$V$20,1,16) -> 594375000 | G40: =INDEX('Consumer Model'!$C$20:$V$20,1,20) -> 1188750000

Sheet Crossover Analysis
A1: CROSSOVER ANALYSIS — what would it take for AUM to overtake the T-bill sleeve?
A2: AUM fee revenue = AUM x fee. NIM revenue = balances x T-bill rate x sleeve. Setting them equal gives a single required ratio of AUM to wallet balances.
A4: THE ALGEBRA
B5: T-bill rate x sleeve % (NIM rate on balances) | C5: =Assumptions!$C$5*Assumptions!$C$6 -> 0.0096
B6: AUM fee rate | C6: =Assumptions!$C$12 -> 0.005
B7: REQUIRED AUM as multiple of wallet balances | C7: =C5/C6 -> 1.92 | H7: total AUM must exceed this x total balances
A9: WHERE THE MODEL ACTUALLY LANDS
B10: Metric | C10: Year 1 | D10: Year 2 | E10: Year 3 | F10: Year 4 | G10: Year 5
B11: Total AUM (year end) | C11: ='Revenue Comparison'!C$39 -> 0 | D11: ='Revenue Comparison'!D$39 -> 15438488 | E11: ='Revenue Comparison'!E$39 -> 65492944 | F11: ='Revenue Comparison'!F$39 -> 2.1191114e+08 | G11: ='Revenue Comparison'!G$39 -> 4.7482754e+08
B12: Total wallet balances (year end) | C12: ='Revenue Comparison'!C$40 -> 18900000 | D12: ='Revenue Comparison'!D$40 -> 74681250 | E12: ='Revenue Comparison'!E$40 -> 237750000 | F12: ='Revenue Comparison'!F$40 -> 594375000 | G12: ='Revenue Comparison'!G$40 -> 1188750000
B13: Actual AUM / balances | C13: =C11/C12 -> 0 | D13: =D11/D12 -> 0.20672509 | E13: =E11/E12 -> 0.27546979 | F13: =F11/F12 -> 0.35652768 | G13: =G11/G12 -> 0.39943432
B14: Required ratio (constant) | C14: =$C$7 -> 1.92 | D14: =$C$7 -> 1.92 | E14: =$C$7 -> 1.92 | F14: =$C$7 -> 1.92 | G14: =$C$7 -> 1.92
B15: Shortfall (x) | C15: =IF(C13=0,"no AUM yet",C14/C13) -> no AUM yet | D15: =IF(D13=0,"no AUM yet",D14/D13) -> 9.287697 | E15: =IF(E13=0,"no AUM yet",E14/E13) -> 6.9699112 | F15: =IF(F13=0,"no AUM yet",F14/F13) -> 5.3852761 | G15: =IF(G13=0,"no AUM yet",G14/G13) -> 4.8067978
A17: WHAT WOULD CLOSE THE GAP
B18: Year 5 invest users | C18: =INDEX('AUM Engine'!$C$62:$V$62,1,20) -> 117750
B19: Year 5 AUM per invest user (model) | C19: =INDEX('AUM Engine'!$C$70:$V$70,1,20) -> 4032.5057
B20: Year 5 AUM per invest user REQUIRED | C20: =$C$7*G12/C18 -> 19383.439
B21: Multiple of modelled balance needed | C21: =C20/C19 -> 4.8067978
B22: for reference: Acorns avg balance | C22: 2142 | H22: mass-market micro-investing
B23: for reference: Betterment / Wealthfront avg | C23: 66000 | H23: primary-brokerage tier
A25: SENSITIVITY — REQUIRED AUM/BALANCE RATIO BY SLEEVE AND FEE
B26: AUM fee \ Vaulta sleeve % | C26: 10% | D26: 20% | E26: 35% | F26: 50% | G26: 58%
B27: 0.25% | C27: =Assumptions!$C$5*0.1/0.0025 -> 1.92 | D27: =Assumptions!$C$5*0.2/0.0025 -> 3.84 | E27: =Assumptions!$C$5*0.35/0.0025 -> 6.72 | F27: =Assumptions!$C$5*0.5/0.0025 -> 9.6 | G27: =Assumptions!$C$5*0.58/0.0025 -> 11.136
B28: 0.50% | C28: =Assumptions!$C$5*0.1/0.005 -> 0.96 | D28: =Assumptions!$C$5*0.2/0.005 -> 1.92 | E28: =Assumptions!$C$5*0.35/0.005 -> 3.36 | F28: =Assumptions!$C$5*0.5/0.005 -> 4.8 | G28: =Assumptions!$C$5*0.58/0.005 -> 5.568
B29: 0.75% | C29: =Assumptions!$C$5*0.1/0.0075 -> 0.64 | D29: =Assumptions!$C$5*0.2/0.0075 -> 1.28 | E29: =Assumptions!$C$5*0.35/0.0075 -> 2.24 | F29: =Assumptions!$C$5*0.5/0.0075 -> 3.2 | G29: =Assumptions!$C$5*0.58/0.0075 -> 3.712
B30: 1.00% | C30: =Assumptions!$C$5*0.1/0.01 -> 0.48 | D30: =Assumptions!$C$5*0.2/0.01 -> 0.96 | E30: =Assumptions!$C$5*0.35/0.01 -> 1.68 | F30: =Assumptions!$C$5*0.5/0.01 -> 2.4 | G30: =Assumptions!$C$5*0.58/0.01 -> 2.784
A31: Lower sleeve makes the crossover EASIER: at a 20% sleeve, AUM must reach 1.92x wallet balances; at 58% it must reach 5.57x.
A32: Highlighted cell is the current setting (0.50% fee, 20% sleeve).
A34: READ-THROUGH
B35: • The crossover does not depend on user counts. It is a pure ratio: AUM must exceed (T-bill rate x sleeve) / AUM fee times wallet balances.
B36: • At the researched contribution rates (1.0-3.5% of balance per month) the model cannot reach that ratio inside five years. Contributions alone move AUM/balances by roughly adoption x contribution rate x months.
B37: • The lever that actually moves it is the initial rollover — money transferred in from an existing bank or brokerage at signup — not the monthly drip.
B38: • Raising the AUM fee is the other lever, and it is cheap: at 0.50% Vaulta undercuts Acorns' effective rate on a typical balance by roughly 3x, so there is headroom.

Sheet Segment Unit Economics
A1: SEGMENT UNIT ECONOMICS — at the 20/80 sleeve, with AUM
A2: Steady-state view: each segment's AUM per investor is taken from the Year 5 engine output, so the AUM fee reflects accumulated balances rather than a guess.
B4: Metric | C4: 1 — Underbanked Active | D4: 2 — Dissatisfied Banked | E4: 3 — Primary Bank Switcher | F4: 4 — Crypto-Curious Investor | H4: Blended Y1 | I4: Blended Y3
B5: CAC | C5: =Assumptions!$C$21 -> 40 | D5: =Assumptions!$C$22 -> 57.5 | E5: =Assumptions!$C$23 -> 70 | F5: =Assumptions!$C$24 -> 47.5 | H5: =C5*Assumptions!$C$35 + D5*Assumptions!$C$36 + E5*Assumptions!$C$37 + F5*Assumptions!$C$38 -> 46 | I5: =C5*Assumptions!$E$35 + D5*Assumptions!$E$36 + E5*Assumptions!$E$37 + F5*Assumptions!$E$38 -> 52.75
B6: Wallet balance | C6: =Assumptions!$D$21 -> 900 | D6: =Assumptions!$D$22 -> 2500 | E6: =Assumptions!$D$23 -> 4250 | F6: =Assumptions!$D$24 -> 6000 | H6: =C6*Assumptions!$C$35 + D6*Assumptions!$C$36 + E6*Assumptions!$C$37 + F6*Assumptions!$C$38 -> 1890 | I6: =C6*Assumptions!$E$35 + D6*Assumptions!$E$36 + E6*Assumptions!$E$37 + F6*Assumptions!$E$38 -> 2377.5
B7: Monthly churn | C7: =Assumptions!$E$21 -> 0.0325 | D7: =Assumptions!$E$22 -> 0.0225 | E7: =Assumptions!$E$23 -> 0.0125 | F7: =Assumptions!$E$24 -> 0.015 | H7: =C7*Assumptions!$C$35 + D7*Assumptions!$C$36 + E7*Assumptions!$C$37 + F7*Assumptions!$C$38 -> 0.02775 | I7: =C7*Assumptions!$E$35 + D7*Assumptions!$E$36 + E7*Assumptions!$E$37 + F7*Assumptions!$E$38 -> 0.024125
B8: AUM adoption ceiling | C8: =Assumptions!$F$21 -> 0.08 | D8: =Assumptions!$F$22 -> 0.25 | E8: =Assumptions!$F$23 -> 0.4 | F8: =Assumptions!$F$24 -> 0.7 | H8: =C8*Assumptions!$C$35 + D8*Assumptions!$C$36 + E8*Assumptions!$C$37 + F8*Assumptions!$C$38 -> 0.193 | I8: =C8*Assumptions!$E$35 + D8*Assumptions!$E$36 + E8*Assumptions!$E$37 + F8*Assumptions!$E$38 -> 0.2355
B9: AUM per investor (Yr 5, from engine) | C9: =INDEX('AUM Engine'!$C$20:$V$20,1,20) -> 258.46113 | D9: =INDEX('AUM Engine'!$C$33:$V$33,1,20) -> 1759.2841 | E9: =INDEX('AUM Engine'!$C$46:$V$46,1,20) -> 5015.9154 | F9: =INDEX('AUM Engine'!$C$59:$V$59,1,20) -> 12672.68 | H9: =C9*Assumptions!$C$35 + D9*Assumptions!$C$36 + E9*Assumptions!$C$37 + F9*Assumptions!$C$38 -> 1950.1299 | I9: =C9*Assumptions!$E$35 + D9*Assumptions!$E$36 + E9*Assumptions!$E$37 + F9*Assumptions!$E$38 -> 2268.1605
A11: MONTHLY REVENUE PER CONSUMER
B12: T-bill NIM (20% sleeve) | C12: =C6*Assumptions!$C$5*Assumptions!$C$6/12 -> 0.72 | D12: =D6*Assumptions!$C$5*Assumptions!$C$6/12 -> 2 | E12: =E6*Assumptions!$C$5*Assumptions!$C$6/12 -> 3.4 | F12: =F6*Assumptions!$C$5*Assumptions!$C$6/12 -> 4.8 | H12: =C12*Assumptions!$C$35 + D12*Assumptions!$C$36 + E12*Assumptions!$C$37 + F12*Assumptions!$C$38 -> 1.512 | I12: =C12*Assumptions!$E$35 + D12*Assumptions!$E$36 + E12*Assumptions!$E$37 + F12*Assumptions!$E$38 -> 1.902
B13: memo: monthly spend | C13: =C6*Assumptions!$C$47 -> 180 | D13: =D6*Assumptions!$C$47 -> 500 | E13: =E6*Assumptions!$C$47 -> 850 | F13: =F6*Assumptions!$C$47 -> 1200 | H13: =C13*Assumptions!$C$35 + D13*Assumptions!$C$36 + E13*Assumptions!$C$37 + F13*Assumptions!$C$38 -> 378 | I13: =C13*Assumptions!$E$35 + D13*Assumptions!$E$36 + E13*Assumptions!$E$37 + F13*Assumptions!$E$38 -> 475.5
B14: QR merchant fee | C14: =C13*Assumptions!$C$48*Assumptions!$C$50 -> 0.36 | D14: =D13*Assumptions!$C$48*Assumptions!$C$50 -> 1 | E14: =E13*Assumptions!$C$48*Assumptions!$C$50 -> 1.7 | F14: =F13*Assumptions!$C$48*Assumptions!$C$50 -> 2.4 | H14: =C14*Assumptions!$C$35 + D14*Assumptions!$C$36 + E14*Assumptions!$C$37 + F14*Assumptions!$C$38 -> 0.756 | I14: =C14*Assumptions!$E$35 + D14*Assumptions!$E$36 + E14*Assumptions!$E$37 + F14*Assumptions!$E$38 -> 0.951
B15: Rain interchange (net of txn cost) | C15: =C13*Assumptions!$C$49*Assumptions!$C$51-C13*Assumptions!$C$49/Assumptions!$C$53*Assumptions!$C$52 -> 0.018 | D15: =D13*Assumptions!$C$49*Assumptions!$C$51-D13*Assumptions!$C$49/Assumptions!$C$53*Assumptions!$C$52 -> 0.05 | E15: =E13*Assumptions!$C$49*Assumptions!$C$51-E13*Assumptions!$C$49/Assumptions!$C$53*Assumptions!$C$52 -> 0.085 | F15: =F13*Assumptions!$C$49*Assumptions!$C$51-F13*Assumptions!$C$49/Assumptions!$C$53*Assumptions!$C$52 -> 0.12 | H15: =C15*Assumptions!$C$35 + D15*Assumptions!$C$36 + E15*Assumptions!$C$37 + F15*Assumptions!$C$38 -> 0.0378 | I15: =C15*Assumptions!$E$35 + D15*Assumptions!$E$36 + E15*Assumptions!$E$37 + F15*Assumptions!$E$38 -> 0.04755
B16: AUM fee | C16: =C9*C8*Assumptions!$C$12/12 -> 0.0086153709 | D16: =D9*D8*Assumptions!$C$12/12 -> 0.18325876 | E16: =E9*E8*Assumptions!$C$12/12 -> 0.83598589 | F16: =F9*F8*Assumptions!$C$12/12 -> 3.6961982 | H16: =C16*Assumptions!$C$35 + D16*Assumptions!$C$36 + E16*Assumptions!$C$37 + F16*Assumptions!$C$38 -> 0.42976667 | I16: =C16*Assumptions!$E$35 + D16*Assumptions!$E$36 + E16*Assumptions!$E$37 + F16*Assumptions!$E$38 -> 0.39568962
B17: Infra | C17: =-Assumptions!$C$54 -> -0.5 | D17: =-Assumptions!$C$54 -> -0.5 | E17: =-Assumptions!$C$54 -> -0.5 | F17: =-Assumptions!$C$54 -> -0.5 | H17: =C17*Assumptions!$C$35 + D17*Assumptions!$C$36 + E17*Assumptions!$C$37 + F17*Assumptions!$C$38 -> -0.5 | I17: =C17*Assumptions!$E$35 + D17*Assumptions!$E$36 + E17*Assumptions!$E$37 + F17*Assumptions!$E$38 -> -0.5
B18: NET CONTRIBUTION / month | C18: =C12+C14+C15+C16+C17 -> 0.60661537 | D18: =D12+D14+D15+D16+D17 -> 2.7332588 | E18: =E12+E14+E15+E16+E17 -> 5.5209859 | F18: =F12+F14+F15+F16+F17 -> 10.516198 | H18: =C18*Assumptions!$C$35 + D18*Assumptions!$C$36 + E18*Assumptions!$C$37 + F18*Assumptions!$C$38 -> 2.2355667 | I18: =C18*Assumptions!$E$35 + D18*Assumptions!$E$36 + E18*Assumptions!$E$37 + F18*Assumptions!$E$38 -> 2.7962396
A20: LIFETIME VALUE
B21: memo: decay factor | C21: =(1-C7)/(1+Assumptions!$C$58) -> 0.95629706 | D21: =(1-D7)/(1+Assumptions!$C$58) -> 0.96618127 | E21: =(1-E7)/(1+Assumptions!$C$58) -> 0.97606547 | F21: =(1-F7)/(1+Assumptions!$C$58) -> 0.97359442
B22: Discounted LTV | C22: =C18/(1+Assumptions!$C$58)*(1-C21^Assumptions!$C$59)/(1-C21) -> 12.780163 | D22: =D18/(1+Assumptions!$C$58)*(1-D21^Assumptions!$C$59)/(1-D21) -> 69.74631 | E22: =E18/(1+Assumptions!$C$58)*(1-E21^Assumptions!$C$59)/(1-E21) -> 174.70631 | F22: =F18/(1+Assumptions!$C$58)*(1-F21^Assumptions!$C$59)/(1-F21) -> 314.61562 | H22: =C22*Assumptions!$C$35 + D22*Assumptions!$C$36 + E22*Assumptions!$C$37 + F22*Assumptions!$C$38 -> 60.053552 | I22: =C22*Assumptions!$E$35 + D22*Assumptions!$E$36 + E22*Assumptions!$E$37 + F22*Assumptions!$E$38 -> 77.795623
B23: LTV : CAC | C23: =C22/C5 -> 0.31950406 | D23: =D22/D5 -> 1.2129793 | E23: =E22/E5 -> 2.4958044 | F23: =F22/F5 -> 6.6234867 | H23: =H22/H5 -> 1.305512 | I23: =I22/I5 -> 1.4747985
B24: CAC payback (months) | C24: =IF(C18<=0,"n/a",C5/C18) -> 65.939641 | D24: =IF(D18<=0,"n/a",D5/D18) -> 21.037159 | E24: =IF(E18<=0,"n/a",E5/E18) -> 12.678895 | F24: =IF(F18<=0,"n/a",F5/F18) -> 4.5168414 | H24: =H5/H18 -> 20.576438 | I24: =I5/I18 -> 18.864621
B25: AUM share of contribution | C25: =C16/C18 -> 0.014202362 | D25: =D16/D18 -> 0.067047719 | E25: =E16/E18 -> 0.15141968 | F25: =F16/F18 -> 0.35147666 | H25: =H16/H18 -> 0.1922406 | I25: =I16/I18 -> 0.14150777
A28: SLEEVE SENSITIVITY — BLENDED Y3 LTV:CAC
B29: Vaulta sleeve % | C29: 10% | D29: 20% | E29: 35% | F29: 50% | G29: 58%
B30: Blended Y3 net contribution / month | C30: =(C6*Assumptions!$C$5*0.1/12 + C14 + C15 + C16 + C17)*Assumptions!$E$35 + (D6*Assumptions!$C$5*0.1/12 + D14 + D15 + D16 + D17)*Assumptions!$E$36 + (E6*Assumptions!$C$5*0.1/12 + E14 + E15 + E16 + E17)*Assumptions!$E$37 + (F6*Assumptions!$C$5*0.1/12 + F14 + F15 + F16 + F17)*Assumptions!$E$38 -> 1.8452396 | D30: =(C6*Assumptions!$C$5*0.2/12 + C14 + C15 + C16 + C17)*Assumptions!$E$35 + (D6*Assumptions!$C$5*0.2/12 + D14 + D15 + D16 + D17)*Assumptions!$E$36 + (E6*Assumptions!$C$5*0.2/12 + E14 + E15 + E16 + E17)*Assumptions!$E$37 + (F6*Assumptions!$C$5*0.2/12 + F14 + F15 + F16 + F17)*Assumptions!$E$38 -> 2.7962396 | E30: =(C6*Assumptions!$C$5*0.35/12 + C14 + C15 + C16 + C17)*Assumptions!$E$35 + (D6*Assumptions!$C$5*0.35/12 + D14 + D15 + D16 + D17)*Assumptions!$E$36 + (E6*Assumptions!$C$5*0.35/12 + E14 + E15 + E16 + E17)*Assumptions!$E$37 + (F6*Assumptions!$C$5*0.35/12 + F14 + F15 + F16 + F17)*Assumptions!$E$38 -> 4.2227396 | F30: =(C6*Assumptions!$C$5*0.5/12 + C14 + C15 + C16 + C17)*Assumptions!$E$35 + (D6*Assumptions!$C$5*0.5/12 + D14 + D15 + D16 + D17)*Assumptions!$E$36 + (E6*Assumptions!$C$5*0.5/12 + E14 + E15 + E16 + E17)*Assumptions!$E$37 + (F6*Assumptions!$C$5*0.5/12 + F14 + F15 + F16 + F17)*Assumptions!$E$38 -> 5.6492396 | G30: =(C6*Assumptions!$C$5*0.58/12 + C14 + C15 + C16 + C17)*Assumptions!$E$35 + (D6*Assumptions!$C$5*0.58/12 + D14 + D15 + D16 + D17)*Assumptions!$E$36 + (E6*Assumptions!$C$5*0.58/12 + E14 + E15 + E16 + E17)*Assumptions!$E$37 + (F6*Assumptions!$C$5*0.58/12 + F14 + F15 + F16 + F17)*Assumptions!$E$38 -> 6.4100396
A31: The sleeve is the single biggest driver of consumer unit economics. Moving from 58% to 20% hands the consumer a 3.84% effective reward rate but cuts Vaulta's per-consumer NIM by about two thirds.

Sheet Sensitivity
A1: SENSITIVITY — Year 5 AUM fee revenue
A2: Both grids recompute from the Assumptions sheet. They vary one driver at a time around the researched defaults.
A4: YEAR 5 AUM / WALLET-BALANCE RATIO vs rollover multiple and contribution rate
A5: Approximation: adoption x (rollover + contribution rate x months invested). Months invested is weighted by the availability ramp.
B6: contribution %/mo \ rollover x | C6: 0.0x | D6: 0.5x | E6: 1.0x | F6: 2.0x | G6: 4.0x | H6: 8.0x
B7: 1% | C7: =INDEX('AUM Engine'!$C$71:$V$71,1,20)*(0+0.01*36) -> 0.08478 | D7: =INDEX('AUM Engine'!$C$71:$V$71,1,20)*(0.5+0.01*36) -> 0.20253 | E7: =INDEX('AUM Engine'!$C$71:$V$71,1,20)*(1+0.01*36) -> 0.32028 | F7: =INDEX('AUM Engine'!$C$71:$V$71,1,20)*(2+0.01*36) -> 0.55578 | G7: =INDEX('AUM Engine'!$C$71:$V$71,1,20)*(4+0.01*36) -> 1.02678 | H7: =INDEX('AUM Engine'!$C$71:$V$71,1,20)*(8+0.01*36) -> 1.96878
B8: 2% | C8: =INDEX('AUM Engine'!$C$71:$V$71,1,20)*(0+0.02*36) -> 0.16956 | D8: =INDEX('AUM Engine'!$C$71:$V$71,1,20)*(0.5+0.02*36) -> 0.28731 | E8: =INDEX('AUM Engine'!$C$71:$V$71,1,20)*(1+0.02*36) -> 0.40506 | F8: =INDEX('AUM Engine'!$C$71:$V$71,1,20)*(2+0.02*36) -> 0.64056 | G8: =INDEX('AUM Engine'!$C$71:$V$71,1,20)*(4+0.02*36) -> 1.11156 | H8: =INDEX('AUM Engine'!$C$71:$V$71,1,20)*(8+0.02*36) -> 2.05356
B9: 3% | C9: =INDEX('AUM Engine'!$C$71:$V$71,1,20)*(0+0.03*36) -> 0.25434 | D9: =INDEX('AUM Engine'!$C$71:$V$71,1,20)*(0.5+0.03*36) -> 0.37209 | E9: =INDEX('AUM Engine'!$C$71:$V$71,1,20)*(1+0.03*36) -> 0.48984 | F9: =INDEX('AUM Engine'!$C$71:$V$71,1,20)*(2+0.03*36) -> 0.72534 | G9: =INDEX('AUM Engine'!$C$71:$V$71,1,20)*(4+0.03*36) -> 1.19634 | H9: =INDEX('AUM Engine'!$C$71:$V$71,1,20)*(8+0.03*36) -> 2.13834
B10: 5% | C10: =INDEX('AUM Engine'!$C$71:$V$71,1,20)*(0+0.05*36) -> 0.4239 | D10: =INDEX('AUM Engine'!$C$71:$V$71,1,20)*(0.5+0.05*36) -> 0.54165 | E10: =INDEX('AUM Engine'!$C$71:$V$71,1,20)*(1+0.05*36) -> 0.6594 | F10: =INDEX('AUM Engine'!$C$71:$V$71,1,20)*(2+0.05*36) -> 0.8949 | G10: =INDEX('AUM Engine'!$C$71:$V$71,1,20)*(4+0.05*36) -> 1.3659 | H10: =INDEX('AUM Engine'!$C$71:$V$71,1,20)*(8+0.05*36) -> 2.3079
B11: 8% | C11: =INDEX('AUM Engine'!$C$71:$V$71,1,20)*(0+0.08*36) -> 0.67824 | D11: =INDEX('AUM Engine'!$C$71:$V$71,1,20)*(0.5+0.08*36) -> 0.79599 | E11: =INDEX('AUM Engine'!$C$71:$V$71,1,20)*(1+0.08*36) -> 0.91374 | F11: =INDEX('AUM Engine'!$C$71:$V$71,1,20)*(2+0.08*36) -> 1.14924 | G11: =INDEX('AUM Engine'!$C$71:$V$71,1,20)*(4+0.08*36) -> 1.62024 | H11: =INDEX('AUM Engine'!$C$71:$V$71,1,20)*(8+0.08*36) -> 2.56224
B12: Required ratio to overtake NIM | C12: ='Crossover Analysis'!$C$7 -> 1.92
A14: Cells at or above the required ratio are combinations where AUM fee revenue exceeds T-bill NIM in Year 5.
A16: YEAR 5 AUM FEE REVENUE vs AUM fee rate
B17: AUM fee | C17: 0.25% | D17: 0.50% | E17: 0.75% | F17: 1.00% | G17: 1.50%
B18: Year 5 AUM fee revenue | C18: ='Revenue Comparison'!$G$39*0.0025 -> 1187068.9 | D18: ='Revenue Comparison'!$G$39*0.005 -> 2374137.7 | E18: ='Revenue Comparison'!$G$39*0.0075 -> 3561206.6 | F18: ='Revenue Comparison'!$G$39*0.01 -> 4748275.4 | G18: ='Revenue Comparison'!$G$39*0.015 -> 7122413.1
B19: vs Year 5 T-bill NIM | C19: ='Revenue Comparison'!$G$32 -> 8252607.1 | D19: ='Revenue Comparison'!$G$32 -> 8252607.1 | E19: ='Revenue Comparison'!$G$32 -> 8252607.1 | F19: ='Revenue Comparison'!$G$32 -> 8252607.1 | G19: ='Revenue Comparison'!$G$32 -> 8252607.1
B20: AUM / NIM | C20: =C18/C19 -> 0.14384168 | D20: =D18/D19 -> 0.28768336 | E20: =E18/E19 -> 0.43152504 | F20: =F18/F19 -> 0.57536672 | G20: =G18/G19 -> 0.86305007
A22: Acorns' flat $3/month is roughly 1.7% of its average balance, so even 1.50% here would undercut the closest mass-market comparable.
